Workbook

Sheet 00 Start Here
A1: Enterprise AI Architecture — Owner-Led Learning and Execution Tracker v1.3.4
A2: Objective: learn and own the complete enterprise AI decision flow under FOUR APPROVAL GATES PLUS OWNER TESTING AND WEEKLY LEARNING; Codex writes only inside explicit gates and the owner executes every command.
A4: FOUR APPROVAL GATES PLUS OWNER TESTING AND WEEKLY LEARNING | E4: Operating rules
A5: 1 | B5: Review dashboard and owner inputs | C5: Choose restart or resume later; preserve historical status until you decide. | E5: MUST — required for the six-week MVP and weekly gate.
A6: 2 | B6: Paste CTX-001 and CTRL-001 | C6: Set the architecture context and the code-only/owner-execution boundary. | E6: SHOULD — hardening or AWS deployment value; defer only with owner-recorded risk.
A7: 3 | B7: Gate 1 — paste one Main Prompt | C7: Codex performs complete read-only impact analysis and returns one consolidated plan; no edits or execution. | E7: OPTIONAL — learn/adopt only when a measured requirement justifies cost/complexity.
A8: 4 | B8: Review impact matrix and decide | C8: Confirm business purpose, architecture, all producers/consumers, exact paths, tests, access, cost, rollback, teardown and all owner decisions together. | E8: Codex writes code; the owner runs every test, deployment, rollback, teardown and access-sensitive command.
A9: 5 | B9: Gate 2 — paste Column L approval | C9: Use exact Code Edit Approval, or bounded Content Edit Approval for document/governance tasks. Baseline drift blocks editing. | E9: A failure produces diagnosis and one owner command at a time; source fixes require a new Code Edit Approval.
A10: 6 | B10: Receive bounded changes and owner guide | C10: Codex reports the read-only diff, complete owner execution order and post-implementation learning summary; Codex runs nothing. | E10: Documentation is a separate approved stage and must state business value in clear wording.
A11: 7 | B11: Owner executes TEST-001 | C11: Run one command at a time with cache-safe scopes and stop conditions; failures receive complete impact analysis before one consolidated remediation approval. | E11: Final approval follows owner testing and document review; Codex never self-approves.
A12: 8 | B12: Gate 3 — paste Column M approval | C12: Codex writes only exact approved documentation and returns the complete Column M Approved Document Manifest. | E12: Weekly learning is mandatory before progressing: business story, technical deep-dive, layman analogy and interview teach-back.
A13: 9 | B13: Gate 4 — paste Column N approval | C13: Codex preflights and closes every manifest document, records owner-supplied reviewer/decision/date and returns full reconciliation. | E13: Editable project inputs — owner maintained
A14: 10 | B14: Owner updates tracker; complete weekly learning | C14: Only after complete Column N closure, update Excel yourself and complete the mandatory end-of-week teach-back before progression. | E14: Project start date
E15: Owner | F15: Gyan Prakash Rai
E16: Current week | F16: Week 2
E17: Monthly sandbox budget | F17: TODO
E18: Restart / resume decision | F18: Resume
A19: Source precedence remains unchanged. This version changes execution ownership and learning controls only: Codex writes approved code; the owner tests, deploys, remediates and approves.

Sheet 01 Dashboard
A1: Execution Dashboard
A2: All KPIs are formula-driven from tracker sheets. Historical status is preserved; the owner executes tests/deployments and updates source records after final approval.
A4: Total steps | D4: Done | G4: Overall progress | J4: Blocked
A5: =COUNTA('02 Master Plan'!$A$6:$A$120) -> 80 | D5: =COUNTIF('02 Master Plan'!$S$6:$S$120,"Done") -> 18 | G5: =IF(A5=0,0,D5/A5) -> 0.225 | J5: =COUNTIF('02 Master Plan'!$S$6:$S$120,"Blocked") -> 0
A7: Open owner TODOs | D7: Tests passed | G7: Decisions approved | J7: Lifecycle tests passed
A8: =COUNTIFS('13 Owner TODOs'!$F$6:$F$80,"<>Done",'13 Owner TODOs'!$A$6:$A$80,"<>") -> 15 | D8: =COUNTIF('11 Test Evidence'!$H$6:$H$80,"Pass") -> 6 | G8: =COUNTIF('12 Decision Log'!$C$6:$C$60,"Baseline Approved")+COUNTIF('12 Decision Log'!$C$6:$C$60,"Approved") -> 18 | J8: =COUNTIFS('11 Test Evidence'!$C$6:$C$80,"Teardown",'11 Test Evidence'!$H$6:$H$80,"Pass") -> 1
A12: Week | B12: Total | C12: Done | D12: Progress | E12: Blocked | G12: Week | H12: Progress
A13: Week 1 | B13: =COUNTIF('02 Master Plan'!$B$6:$B$120,A13) -> 13 | C13: =COUNTIFS('02 Master Plan'!$B$6:$B$120,A13,'02 Master Plan'!$S$6:$S$120,"Done") -> 13 | D13: =IF(B13=0,0,C13/B13) -> 1 | E13: =COUNTIFS('02 Master Plan'!$B$6:$B$120,A13,'02 Master Plan'!$S$6:$S$120,"Blocked") -> 0 | G13: =A13 -> Week 1 | H13: =D13 -> 1
A14: Week 2 | B14: =COUNTIF('02 Master Plan'!$B$6:$B$120,A14) -> 13 | C14: =COUNTIFS('02 Master Plan'!$B$6:$B$120,A14,'02 Master Plan'!$S$6:$S$120,"Done") -> 5 | D14: =IF(B14=0,0,C14/B14) -> 0.38461538 | E14: =COUNTIFS('02 Master Plan'!$B$6:$B$120,A14,'02 Master Plan'!$S$6:$S$120,"Blocked") -> 0 | G14: =A14 -> Week 2 | H14: =D14 -> 0.38461538
A15: Week 3 | B15: =COUNTIF('02 Master Plan'!$B$6:$B$120,A15) -> 13 | C15: =COUNTIFS('02 Master Plan'!$B$6:$B$120,A15,'02 Master Plan'!$S$6:$S$120,"Done") -> 0 | D15: =IF(B15=0,0,C15/B15) -> 0 | E15: =COUNTIFS('02 Master Plan'!$B$6:$B$120,A15,'02 Master Plan'!$S$6:$S$120,"Blocked") -> 0 | G15: =A15 -> Week 3 | H15: =D15 -> 0
A16: Week 4 | B16: =COUNTIF('02 Master Plan'!$B$6:$B$120,A16) -> 13 | C16: =COUNTIFS('02 Master Plan'!$B$6:$B$120,A16,'02 Master Plan'!$S$6:$S$120,"Done") -> 0 | D16: =IF(B16=0,0,C16/B16) -> 0 | E16: =COUNTIFS('02 Master Plan'!$B$6:$B$120,A16,'02 Master Plan'!$S$6:$S$120,"Blocked") -> 0 | G16: =A16 -> Week 4 | H16: =D16 -> 0
A17: Week 5 | B17: =COUNTIF('02 Master Plan'!$B$6:$B$120,A17) -> 14 | C17: =COUNTIFS('02 Master Plan'!$B$6:$B$120,A17,'02 Master Plan'!$S$6:$S$120,"Done") -> 0 | D17: =IF(B17=0,0,C17/B17) -> 0 | E17: =COUNTIFS('02 Master Plan'!$B$6:$B$120,A17,'02 Master Plan'!$S$6:$S$120,"Blocked") -> 0 | G17: =A17 -> Week 5 | H17: =D17 -> 0
A18: Week 6 | B18: =COUNTIF('02 Master Plan'!$B$6:$B$120,A18) -> 14 | C18: =COUNTIFS('02 Master Plan'!$B$6:$B$120,A18,'02 Master Plan'!$S$6:$S$120,"Done") -> 0 | D18: =IF(B18=0,0,C18/B18) -> 0 | E18: =COUNTIFS('02 Master Plan'!$B$6:$B$120,A18,'02 Master Plan'!$S$6:$S$120,"Blocked") -> 0 | G18: =A18 -> Week 6 | H18: =D18 -> 0
A21: Weekly gate interpretation
A22: READY: every MUST task is Done, tests have evidence and the owner signs off.
A23: BLOCKED: stop new prompts; resolve the dependency or explicitly defer with risk/owner/date.
A24: IN PROGRESS: Codex writes approved code only; the owner follows TEST-001 guidance and returns each command result.
A25: Done requires owner-executed validation, approved business-first documentation, rollback/teardown evidence and final owner approval.
A26: Cloud mutations remain manual even when every automated gate passes.

Sheet 02 Master Plan
A1: Master Six-Week Owner-Led Learning Plan — v1.3.4
A2: Historical statuses, evidence, notes and dates are preserved. Prompt execution follows FOUR APPROVAL GATES PLUS OWNER TESTING AND WEEKLY LEARNING; complete-impact review precedes any bounded edit, and only the owner updates tracker progress.
A5: Step ID | B5: Week | C5: Seq | D5: Priority | E5: Workstream | F5: Task / Outcome | G5: Why It Matters | H5: Owner | I5: Effort (h) | J5: Prompt ID | K5: User TODO IDs | L5: Acceptance Criteria | M5: Owner Verification Command | N5: Expected Result | O5: Evidence Path | P5: Decision ID | Q5: Dependency | R5: Rollback / Teardown | S5: Status | T5: Notes | U5: Task Context
A6: W1-01 | B6: Week 1 | C6: 1 | D6: MUST | E6: Scope | F6: Confirm the first use case, user group, exclusions and measurable MVP outcome. | G6: A narrow use case prevents a platform-without-a-problem and sets evaluation truth. | H6: User | I6: 1 | J6: W1-MVP-001 | K6: USE-001, DATA-001, EVAL-001 | L6: One approved one-page scope and 5 representative questions. | M6: Owner review of docs/features/MVP-001.md | N6: Scope, exclusions and success measures approved. | O6: docs/features/MVP-001.md | P6: ADR-001 | Q6: None | R6: Revert scope file before implementation begins. | S6: Done | T6: Use W1-MVP-001. Approve five starter questions now; the full 25+ golden dataset is completed under W3-002 in Week 3. | Implementation commit 210381c3ddbc9aab83ccaeb11a59db8d8dad549b; owner approval date 2026-08-18; owner reaffirmed 2026-08-18T16:01:18Z. | U6: Week 1 business/decision documentation task in Scope. The owner provides or approves the facts; after Document Writing Approval, Codex may draft only the approved business-first documentation. No code or command execution is permitted. Business value: A narrow use case prevents a platform-without-a-problem and sets evaluation truth. Interview focus: explain the decision, its alternatives and downstream impact.
A7: W1-02 | B7: Week 1 | C7: 2 | D7: MUST | E7: Governance | F7: Record source precedence: v1.1 controls override older schedule while preserving technical prompts. | G7: Prevents Codex and coach from following conflicting weekly sequences. | H7: User (execute) + Codex (guide/code) | I7: 0.5 | J7: W1-GOV-001 | K7: None | L7: Decision recorded and referenced by all feature prompts. | M7: Review docs/adr/ADR-000-source-precedence.md | N7: v1.1 is named implementation authority. | O7: docs/adr/ADR-000-source-precedence.md | P7: ADR-016 | Q7: W1-01 | R7: Restore prior ADR only through reviewed superseding decision. | S7: Done | T7: Use W1-GOV-001. Create ADR-000 only; docs/codex files are not prerequisites for this task. | Implementation commit 210381c3ddbc9aab83ccaeb11a59db8d8dad549b; owner approval date 2026-08-18; owner reaffirmed 2026-08-18T16:01:18Z. | U7: Week 1 business/decision documentation task in Governance. The owner provides or approves the facts; after Document Writing Approval, Codex may draft only the approved business-first documentation. No code or command execution is permitted. Business value: Prevents Codex and coach from following conflicting weekly sequences. Interview focus: explain the decision, its alternatives and downstream impact.
A8: W1-03 | B8: Week 1 | C8: 3 | D8: MUST | E8: Repository | F8: Create the monorepo and documentation/evidence structure. | G8: Gives every change an auditable home and supports clean ownership. | H8: Codex (code) + User (execute) | I8: 1.5 | J8: W1-001 | K8: TAG-001 | L8: Required folders, README and Makefile exist. | M8: find . -maxdepth 3 -type d | sort | N8: Layout matches blueprint; no unrelated files changed. | O8: docs/test-evidence/W1-03-layout.txt | P8: ADR-016 | Q8: W1-02 | R8: Delete only newly created empty skeleton paths after diff review. | S8: Done | T8: Implementation commit 210381c3ddbc9aab83ccaeb11a59db8d8dad549b; owner approval date 2026-08-18; owner reaffirmed 2026-08-18T16:01:18Z. | U8: Week 1 Repository task in the end-to-end architecture. After Code Edit Approval, Codex writes only the approved code/configuration/test code for “Create the monorepo and documentation/evidence structure.”; you run the verification/deployment commands and return the results. Business value: Gives every change an auditable home and supports clean ownership. Interview focus: explain where this component sits, how it fails safely and how it is rolled back.
A9: W1-04 | B9: Week 1 | C9: 4 | D9: MUST | E9: Traceability | F9: Create feature-matrix.yaml and the first feature record. | G9: Links purpose, files, tests, cost, approval, rollback and teardown. | H9: Codex (code) + User (execute) | I9: 1 | J9: W1-001 | K9: USE-001, TAG-001 | L9: Schema validates and feature MVP-001 is planned. | M9: python tools/validate_feature_matrix.py | N9: Validation exits 0; missing required fields fail. | O9: docs/test-evidence/W1-04-feature-matrix.json | P9: ADR-016 | Q9: W1-03 | R9: Restore previous matrix version from Git. | S9: Done | T9: Implementation commit 210381c3ddbc9aab83ccaeb11a59db8d8dad549b; owner approval date 2026-08-18; owner reaffirmed 2026-08-18T16:01:18Z. | U9: Week 1 Traceability task in the end-to-end architecture. After Code Edit Approval, Codex writes only the approved code/configuration/test code for “Create feature-matrix.yaml and the first feature record.”; you run the verification/deployment commands and return the results. Business value: Links purpose, files, tests, cost, approval, rollback and teardown. Interview focus: explain where this component sits, how it fails safely and how it is rolled back.
A10: W1-05 | B10: Week 1 | C10: 5 | D10: MUST | E10: Python foundation | F10: Create reproducible dependencies and typed configuration. | G10: Fail-fast configuration and portable dependencies reduce hidden runtime risk. | H10: Codex (code) + User (execute) | I10: 1.5 | J10: W1-002 | K10: AWS-002, BED-001, EMB-001 | L10: pip install succeeds; config tests pass offline. | M10: pip install -r requirements.txt && pytest tests/unit/test_config.py -q | N10: No paid/network dependency in unit tests; TODOs remain non-secret. | O10: docs/test-evidence/W1-05-config.txt | P10: ADR-002 | Q10: W1-03 | R10: Revert dependency/config commit and recreate virtual environment. | S10: Done | T10: Implementation commit 210381c3ddbc9aab83ccaeb11a59db8d8dad549b; owner approval date 2026-08-18; owner reaffirmed 2026-08-18T16:01:18Z. | U10: Week 1 Python foundation task in the end-to-end architecture. After Code Edit Approval, Codex writes only the approved code/configuration/test code for “Create reproducible dependencies and typed configuration.”; you run the verification/deployment commands and return the results. Business value: Fail-fast configuration and portable dependencies reduce hidden runtime risk. Interview focus: explain where this component sits, how it fails safely and how it is rolled back.
A11: W1-06 | B11: Week 1 | C11: 6 | D11: MUST | E11: Testing | F11: Create pytest layers, deterministic fakes and evidence capture. | G11: Testing is a feature gate, not an afterthought. | H11: Codex (code) + User (execute) | I11: 1.25 | J11: W1-003 | K11: None | L11: Markers and sample feature test run locally. | M11: pytest tests/unit tests/feature -q | N11: Tests pass; evidence metadata excludes secrets/content. | O11: docs/test-evidence/W1-06-tests.json | P11: ADR-017 | Q11: W1-04,W1-05 | R11: Revert test framework commit; no platform resources exist. | S11: Done | T11: Implementation commit 210381c3ddbc9aab83ccaeb11a59db8d8dad549b; owner approval date 2026-08-18; owner reaffirmed 2026-08-18T16:01:18Z. | U11: Week 1 Testing task in the end-to-end architecture. After Code Edit Approval, Codex writes only the approved code/configuration/test code for “Create pytest layers, deterministic fakes and evidence capture.”; you run the verification/deployment commands and return the results. Business value: Testing is a feature gate, not an afterthought. Interview focus: explain where this component sits, how it fails safely and how it is rolled back.
A12: W1-07 | B12: Week 1 | C12: 7 | D12: MUST | E12: Developer controls | F12: Add Make targets for preflight, test, scan, plan, rollback, destroy-plan and verify-clean. | G12: A single, reviewable command vocabulary keeps user and Codex synchronized. | H12: Codex (code) + User (execute) | I12: 1 | J12: W1-001 | K12: None | L12: Make help documents safe commands; mutating commands are gated. | M12: make help && make preflight | N12: Preflight passes; apply/destroy are never default dependencies. | O12: docs/test-evidence/W1-07-make.txt | P12: ADR-010, ADR-011 | Q12: W1-03 | R12: Revert Makefile changes. | S12: Done | T12: Implementation commit 210381c3ddbc9aab83ccaeb11a59db8d8dad549b; owner approval date 2026-08-18; owner reaffirmed 2026-08-18T16:01:18Z. | U12: Week 1 Developer controls task in the end-to-end architecture. After Code Edit Approval, Codex writes only the approved code/configuration/test code for “Add Make targets for preflight, test, scan, plan, rollback, destroy-plan and verify-clean.”; you run the verification/deployment commands and return the results. Business value: A single, reviewable command vocabulary keeps user and Codex synchronized. Interview focus: explain where this component sits, how it fails safely and how it is rolled back.
A13: W1-08 | B13: Week 1 | C13: 8 | D13: MUST | E13: DevSecOps | F13: Add pre-commit formatting, linting and secret scanning baseline. | G13: Shift-left checks stop secrets and poor-quality changes before PR. | H13: Codex (code) + User (execute) | I13: 1 | J13: W1-003 | K13: SEC-003 | L13: Insecure secret fixture is blocked without committing a real secret. | M13: pre-commit run --all-files | N13: All checks pass on source; synthetic fixture produces expected failure. | O13: docs/test-evidence/W1-08-precommit.txt | P13: ADR-017 | Q13: W1-05 | R13: Revert hooks only after owner review; rotate any accidentally exposed credential. | S13: Done | T13: Implementation commit 210381c3ddbc9aab83ccaeb11a59db8d8dad549b; owner approval date 2026-08-18; owner reaffirmed 2026-08-18T16:01:18Z. | U13: Week 1 DevSecOps task in the end-to-end architecture. After Code Edit Approval, Codex writes only the approved code/configuration/test code for “Add pre-commit formatting, linting and secret scanning baseline.”; you run the verification/deployment commands and return the results. Business value: Shift-left checks stop secrets and poor-quality changes before PR. Interview focus: explain where this component sits, how it fails safely and how it is rolled back.
A14: W1-09 | B14: Week 1 | C14: 9 | D14: MUST | E14: Terraform lifecycle | F14: Separate infra/bootstrap from infra/environments/sandbox and document state removal last. | G14: A platform cannot fully disappear if its state backend is embedded in the same lifecycle. | H14: Codex (code) + User (execute) | I14: 1.25 | J14: W1-004 | K14: AWS-001, AWS-002, TAG-001 | L14: Two roots validate as skeletons and dependency order is documented. | M14: terraform -chdir=infra/bootstrap fmt -check && terraform -chdir=infra/environments/sandbox fmt -check | N14: No resource apply; backend/platform boundaries are explicit. | O14: docs/test-evidence/W1-09-roots.txt | P14: ADR-009 | Q14: W1-03 | R14: Revert Terraform skeleton; no state exists yet. | S14: Done | T14: Implementation commit 210381c3ddbc9aab83ccaeb11a59db8d8dad549b; owner approval date 2026-08-18; owner reaffirmed 2026-08-18T16:01:18Z. | W1-004 historical disclosure preserved: commit d3e5ad182fac38dbf166c6ce15b8ade8868379da contained 34 intended paths plus 1 owner workbook path; consolidated commit 210381c3ddbc9aab83ccaeb11a59db8d8dad549b excludes the workbook. | U14: Week 1 Terraform lifecycle task in the end-to-end architecture. After Code Edit Approval, Codex writes only the approved code/configuration/test code for “Separate infra/bootstrap from infra/environments/sandbox and document state removal last.”; you run the verification/deployment commands and return the results. Business value: A platform cannot fully disappear if its state backend is embedded in the same lifecycle. Interview focus: explain where this component sits, how it fails safely and how it is rolled back.
A15: W1-10 | B15: Week 1 | C15: 10 | D15: MUST | E15: Reversibility | F15: Create platformctl command contracts with dry-run and approvals. | G15: Deploy, rollback and teardown need distinct safe semantics. | H15: Codex (code) + User (execute) | I15: 1.5 | J15: W1-004 | K15: DEST-001, KMS-001 | L15: CLI help and unit tests prove confirmation/approval gates. | M15: python -m tools.platformctl --help && pytest tests/unit/test_platformctl.py -q | N15: No command mutates by default; missing approval fails closed. | O15: docs/test-evidence/W1-10-platformctl.txt | P15: ADR-010, ADR-011, ADR-012 | Q15: W1-09 | R15: Revert CLI commit; no cloud mutation is allowed. | S15: Done | T15: Implementation commit 210381c3ddbc9aab83ccaeb11a59db8d8dad549b; owner approval date 2026-08-18; owner reaffirmed 2026-08-18T16:01:18Z. | W1-004 historical disclosure preserved: commit d3e5ad182fac38dbf166c6ce15b8ade8868379da contained 34 intended paths plus 1 owner workbook path; consolidated commit 210381c3ddbc9aab83ccaeb11a59db8d8dad549b excludes the workbook. | U15: Week 1 Reversibility task in the end-to-end architecture. After Code Edit Approval, Codex writes only the approved code/configuration/test code for “Create platformctl command contracts with dry-run and approvals.”; you run the verification/deployment commands and return the results. Business value: Deploy, rollback and teardown need distinct safe semantics. Interview focus: explain where this component sits, how it fails safely and how it is rolled back.
A16: W1-11 | B16: Week 1 | C16: 11 | D16: MUST | E16: Cleanup verification | F16: Implement mocked tag and service-specific residual checks. | G16: Tag-only discovery misses some resources; native checks close the gap. | H16: Codex (code) + User (execute) | I16: 1 | J16: W1-004 | K16: TAG-001, KMS-001 | L16: Mock orphan makes verify-clean fail; PendingDeletion key is documented exception. | M16: pytest tests/teardown -q | N16: Expected pass/fail matrix is recorded. | O16: docs/test-evidence/W1-11-cleanup.json | P16: ADR-013, ADR-014 | Q16: W1-10 | R16: Revert verifier implementation; keep the control requirement. | S16: Done | T16: Implementation commit 210381c3ddbc9aab83ccaeb11a59db8d8dad549b; owner approval date 2026-08-18; owner reaffirmed 2026-08-18T16:01:18Z. | W1-004 historical disclosure preserved: commit d3e5ad182fac38dbf166c6ce15b8ade8868379da contained 34 intended paths plus 1 owner workbook path; consolidated commit 210381c3ddbc9aab83ccaeb11a59db8d8dad549b excludes the workbook. | U16: Week 1 Cleanup verification task in the end-to-end architecture. After Code Edit Approval, Codex writes only the approved code/configuration/test code for “Implement mocked tag and service-specific residual checks.”; you run the verification/deployment commands and return the results. Business value: Tag-only discovery misses some resources; native checks close the gap. Interview focus: explain where this component sits, how it fails safely and how it is rolled back.
A17: W1-12 | B17: Week 1 | C17: 12 | D17: MUST | E17: Checkpoint | F17: Review diffs, architecture decisions, test evidence and Week 2 readiness. | G17: Owner approval is the stop point between features/weeks. | H17: User | I17: 1 | J17: W1-REVIEW-001 | K17: All Week 1 TODOs | L17: Every MUST step is Done; no blocker or unapproved scope remains. | M17: make preflight && make test | N17: Owner sign-off recorded with outstanding items explicitly deferred. | O17: docs/deployment-records/W1-signoff.md | P17: ADR-016 | Q17: W1-01:W1-11 | R17: No Week 2 prompt is used until gaps are resolved. | S17: Done | T17: W1-12 readiness PASS; final Week 1 sign-off APPROVED by Gyan Prakash Rai at 2026-08-19T00:10:55+08:00 (Asia/Singapore); sign-off evidence docs/deployment-records/W1-signoff.md; implementation commit 10f03a483f2ff639081c5b57dacaf282a31aaad4. | U17: Week 1 business/decision documentation task in Checkpoint. The owner provides or approves the facts; after Document Writing Approval, Codex may draft only the approved business-first documentation. No code or command execution is permitted. Business value: Owner approval is the stop point between features/weeks. Interview focus: explain the decision, its alternatives and downstream impact.
A18: W1-13 | B18: Week 1 | C18: 13 | D18: MUST | E18: Weekly learning | F18: Complete the Week 1 business, architecture and interview teach-back. | G18: Turns governance, repository, test and lifecycle controls into an explainable architecture story. | H18: User (execute) + Codex (guide/code) | I18: 1 | J18: WEEKLY-LEARN-001 | K18: None | L18: Owner explains the Week 1 business outcome, control flow, decisions, failure boundaries and three interview answers without reading code. | M18: Owner teach-back; no command | N18: Business summary, technical deep-dive, layman analogy, decision recap and interview Q&A completed. | O18: docs/learning/W1-learning-review.md | P18: Existing Week 1 ADRs | Q18: W1-12 | R18: No runtime rollback; revise the learning note through document approval if inaccurate. | S18: Done | T18: Added in v1.3.0; historical Week 1 completion records remain unchanged. | U18: Week 1 learning gate after all implementation and checkpoint work. Codex teaches the business outcome and architecture; the owner completes a teach-back and interview practice. No runtime action is permitted. Business value: converts completed work into reusable understanding and decision ownership.
A19: W2-01 | B19: Week 2 | C19: 1 | D19: MUST | E19: Data contracts | F19: Implement provider-neutral document, chunk, query, answer and citation models. | G19: Stable domain types make vector and LLM backends replaceable. | H19: Codex (code) + User (execute) | I19: 1 | J19: W2-001 | K19: DATA-002, SEC-001 | L19: Models validate required identity/classification metadata. | M19: pytest tests/unit/test_models.py -q | N19: Invalid tenant/classification input fails. | O19: docs/test-evidence/W2-01-models.txt | P19: ADR-002 | Q19: W1-13 | R19: Revert model commit; no stored vectors affected. | S19: Done | U19: Week 2 Data contracts task in the end-to-end architecture. After Code Edit Approval, Codex writes only the approved code/configuration/test code for “Implement provider-neutral document, chunk, query, answer and citation models.”; you run the verification/deployment commands and return the results. Business value: Stable domain types make vector and LLM backends replaceable. Interview focus: explain where this component sits, how it fails safely and how it is rolled back.
A20: W2-02 | B20: Week 2 | C20: 2 | D20: MUST | E20: Vector interface | F20: Define VectorStore protocol and in-memory fake with contract tests. | G20: Business logic must not depend on Qdrant/OpenSearch SDK objects. | H20: Codex (code) + User (execute) | I20: 1.25 | J20: W2-001 | K20: None | L20: Fake passes all contract tests. | M20: pytest tests/contract/test_vector_store.py -q | N20: Protocol behavior and normalized errors are stable. | O20: docs/test-evidence/W2-02-vector-contract.txt | P20: ADR-002, ADR-003 | Q20: W2-01 | R20: Revert interface only before downstream adapters merge. | S20: Done | U20: Week 2 Vector interface task in the end-to-end architecture. After Code Edit Approval, Codex writes only the approved code/configuration/test code for “Define VectorStore protocol and in-memory fake with contract tests.”; you run the verification/deployment commands and return the results. Business value: Business logic must not depend on Qdrant/OpenSearch SDK objects. Interview focus: explain where this component sits, how it fails safely and how it is rolled back.
A21: W2-03 | B21: Week 2 | C21: 3 | D21: MUST | E21: Local platform | F21: Start pinned Qdrant through Docker Compose with healthcheck. | G21: A real client/server vector store gives useful local integration evidence. | H21: Codex (code) + User (execute) | I21: 1 | J21: W2-001 | K21: None | L21: Qdrant becomes healthy without an embedded credential. | M21: docker compose up -d qdrant && docker compose ps | N21: Service is healthy; image version is pinned. | O21: docs/test-evidence/W2-03-qdrant.txt | P21: ADR-003 | Q21: W1-12 | R21: docker compose down -v; verify no project volume/network. | S21: Done | U21: Week 2 Local platform task in the end-to-end architecture. After Code Edit Approval, Codex writes only the approved code/configuration/test code for “Start pinned Qdrant through Docker Compose with healthcheck.”; you run the verification/deployment commands and return the results. Business value: A real client/server vector store gives useful local integration evidence. Interview focus: explain where this component sits, how it fails safely and how it is rolled back.
A22: W2-04 | B22: Week 2 | C22: 4 | D22: MUST | E22: Vector adapters | F22: Implement Qdrant adapter and OpenSearch adapter boundary. | G22: Local and AWS retrieval must satisfy the same contract. | H22: Codex (code) + User (execute) | I22: 1.5 | J22: W2-001 | K22: AWS-002, NET-001 | L22: Fake/Qdrant tests pass; AWS tests remain marked/skipped. | M22: pytest tests/contract tests/integration/test_qdrant.py -q | N22: No vendor object leaks; timeouts and filters are applied. | O22: docs/test-evidence/W2-04-adapters.txt | P22: ADR-003 | Q22: W2-02,W2-03 | R22: Delete test collection and restore previous adapter version. | S22: Done | U22: Week 2 Vector adapters task in the end-to-end architecture. After Code Edit Approval, Codex writes only the approved code/configuration/test code for “Implement Qdrant adapter and OpenSearch adapter boundary.”; you run the verification/deployment commands and return the results. Business value: Local and AWS retrieval must satisfy the same contract. Interview focus: explain where this component sits, how it fails safely and how it is rolled back.
A23: W2-05 | B23: Week 2 | C23: 5 | D23: MUST | E23: Embeddings | F23: Implement sentence-transformer and deterministic fake embedders. | G23: Local CPU embeddings avoid a paid dependency while preserving provider exit. | H23: Codex (code) + User (execute) | I23: 1.25 | J23: W2-002 | K23: EMB-001 | L23: Batch, normalization and dimension mismatch tests pass. | M23: pytest tests/unit/test_embedder.py -q | N23: Unit tests make no model download; integration model is explicit. | O23: docs/test-evidence/W2-05-embedder.txt | P23: ADR-002 | Q23: W2-01 | R23: Restore previous model configuration and recreate collection if dimension changed. | S23: Not Started | U23: Week 2 Embeddings task in the end-to-end architecture. After Code Edit Approval, Codex writes only the approved code/configuration/test code for “Implement sentence-transformer and deterministic fake embedders.”; you run the verification/deployment commands and return the results. Business value: Local CPU embeddings avoid a paid dependency while preserving provider exit. Interview focus: explain where this component sits, how it fails safely and how it is rolled back.
A24: W2-06 | B24: Week 2 | C24: 6 | D24: MUST | E24: Ingestion | F24: Implement validation, hashing, normalization and deterministic token chunking. | G24: Reproducible chunk IDs/versioning make re-index and deletion safe. | H24: Codex (code) + User (execute) | I24: 1.5 | J24: W2-003 | K24: DATA-001, DATA-002 | L24: Same input produces same IDs; changed version is distinguishable. | M24: pytest tests/unit/test_chunking.py tests/unit/test_ingestion.py -q | N24: Size/type failures quarantine; no raw content in logs. | O24: docs/test-evidence/W2-06-ingestion.txt | P24: ADR-017 | Q24: W2-01,W2-05 | R24: Delete affected document version and re-ingest last approved manifest. | S24: Not Started | U24: Week 2 Ingestion task in the end-to-end architecture. After Code Edit Approval, Codex writes only the approved code/configuration/test code for “Implement validation, hashing, normalization and deterministic token chunking.”; you run the verification/deployment commands and return the results. Business value: Reproducible chunk IDs/versioning make re-index and deletion safe. Interview focus: explain where this component sits, how it fails safely and how it is rolled back.
A25: W2-07 | B25: Week 2 | C25: 7 | D25: MUST | E25: Privacy | F25: Add replaceable Presidio PII detection/redaction hook. | G25: PII handling belongs before indexing and telemetry. | H25: Codex (code) + User (execute) | I25: 1 | J25: W2-003 | K25: DATA-003 | L25: Configured PII is redacted/quarantined and never appears in evidence logs. | M25: pytest tests/security/test_pii.py -q | N25: Synthetic PII fixture is handled as policy states. | O25: docs/test-evidence/W2-07-pii.txt | P25: ADR-006 | Q25: W2-06 | R25: Delete derived chunks; restore approved unredacted source only in controlled location. | S25: Not Started | U25: Week 2 Privacy task in the end-to-end architecture. After Code Edit Approval, Codex writes only the approved code/configuration/test code for “Add replaceable Presidio PII detection/redaction hook.”; you run the verification/deployment commands and return the results. Business value: PII handling belongs before indexing and telemetry. Interview focus: explain where this component sits, how it fails safely and how it is rolled back.
A26: W2-08 | B26: Week 2 | C26: 8 | D26: MUST | E26: Authorization | F26: Enforce tenant/classification filters before vector search. | G26: The model cannot be trusted to enforce access control. | H26: Codex (code) + User (execute) | I26: 1 | J26: W2-001 | K26: SEC-001 | L26: Cross-tenant query returns zero unauthorized chunks. | M26: pytest tests/security/test_tenant_isolation.py -q | N26: 100% isolation test passes. | O26: docs/test-evidence/W2-08-isolation.txt | P26: ADR-006 | Q26: W2-04 | R26: Disable retrieval endpoint and restore last-known-good filter implementation. | S26: Done | U26: Week 2 Authorization task in the end-to-end architecture. After Code Edit Approval, Codex writes only the approved code/configuration/test code for “Enforce tenant/classification filters before vector search.”; you run the verification/deployment commands and return the results. Business value: The model cannot be trusted to enforce access control. Interview focus: explain where this component sits, how it fails safely and how it is rolled back.
A27: W2-09 | B27: Week 2 | C27: 9 | D27: MUST | E27: Feature proof | F27: Ingest approved sample corpus and verify top-5 retrieval. | G27: This is the first measurable RAG foundation outcome. | H27: User (execute) + Codex (guide/code) | I27: 1 | J27: W2-004 | K27: DATA-001, EVAL-001 | L27: Expected source appears in top 5 for representative questions. | M27: python -m enterprise_ai.ingestion.pipeline ingest --source data/sample --tenant demo && pytest tests/feature/test_local_retrieval.py -q | N27: Manifest, retrieval scores and source IDs are captured. | O27: docs/test-evidence/W2-09-retrieval.json | P27: ADR-003, ADR-017 | Q27: W2-03:W2-08 | R27: Delete test collection/volume and restore previous config. | S27: Not Started | U27: Week 2 Feature proof task in the end-to-end architecture. After Code Edit Approval, Codex writes only the approved code/configuration/test code for “Ingest approved sample corpus and verify top-5 retrieval.”; you run the verification/deployment commands and return the results. Business value: This is the first measurable RAG foundation outcome. Interview focus: explain where this component sits, how it fails safely and how it is rolled back.
A28: W2-10 | B28: Week 2 | C28: 10 | D28: MUST | E28: Reversibility | F28: Run local deploy, rollback and complete removal drill. | G28: A working feature is incomplete until it can be removed cleanly. | H28: User (execute) + Codex (guide/code) | I28: 1 | J28: W2-004 | K28: DEST-001 | L28: Previous configuration works after rollback; teardown leaves no local residue. | M28: make rollback-local && make destroy-local && make verify-clean-local | N28: No project container, volume or network remains. | O28: docs/rollback-records/W2-local.md | P28: ADR-012, ADR-013 | Q28: W2-09 | R28: Recreate from pinned Compose/config and re-run feature test. | S28: Not Started | U28: Week 2 Reversibility task in the end-to-end architecture. After Code Edit Approval, Codex writes only the approved code/configuration/test code for “Run local deploy, rollback and complete removal drill.”; you run the verification/deployment commands and return the results. Business value: A working feature is incomplete until it can be removed cleanly. Interview focus: explain where this component sits, how it fails safely and how it is rolled back.
A29: W2-11 | B29: Week 2 | C29: 11 | D29: SHOULD | E29: Learning checkpoint | F29: Explain embeddings, cosine similarity, chunk size/overlap and metadata filtering. | G29: The workbook is also an interview/reference learning plan. | H29: User | I29: 0.75 | J29: W2-LEARN-001 | K29: None | L29: Five-minute explanation uses current implementation evidence. | M29: Record explanation notes in docs/architecture/local-retrieval.md | N29: Explanation connects decisions to quality, security and cost. | O29: docs/architecture/local-retrieval.md | P29: ADR-002, ADR-003, ADR-006 | Q29: W2-09 | R29: Revise ADR/notes; do not change code without a feature cycle. | S29: Not Started | U29: Week 2 owner decision/checkpoint in Learning checkpoint. You choose, approve or execute “Explain embeddings, cosine similarity, chunk size/overlap and metadata filtering.” because the decision affects downstream architecture and risk. Codex explains alternatives and may draft approved wording only under the proper approval stage. Business value: The workbook is also an interview/reference learning plan. Interview focus: explain the decision, trade-off and downstream consequence.
A30: W2-12 | B30: Week 2 | C30: 12 | D30: MUST | E30: Checkpoint | F30: Approve local retrieval gate and Week 3 inputs. | G30: Prevents LLM work from hiding retrieval defects. | H30: User | I30: 0.75 | J30: W2-REVIEW-001 | K30: BED-001, EVAL-001 | L30: All MUST tests and cleanup evidence pass. | M30: make test && make verify-clean-local | N30: Owner sign-off; Bedrock/evaluation TODOs resolved or explicitly mocked. | O30: docs/deployment-records/W2-signoff.md | P30: ADR-016 | Q30: W2-01:W2-11 | R30: Remain on local retrieval until the gate passes. | S30: Not Started | U30: Week 2 business/decision documentation task in Checkpoint. The owner provides or approves the facts; after Document Writing Approval, Codex may draft only the approved business-first documentation. No code or command execution is permitted. Business value: Prevents LLM work from hiding retrieval defects. Interview focus: explain the decision, its alternatives and downstream impact.
A31: W2-13 | B31: Week 2 | C31: 13 | D31: MUST | E31: Weekly learning | F31: Complete the Week 2 local retrieval business, architecture and interview teach-back. | G31: Converts vector retrieval, ingestion, privacy and authorization work into an end-to-end business explanation. | H31: User (execute) + Codex (guide/code) | I31: 1 | J31: WEEKLY-LEARN-001 | K31: None | L31: Owner explains document-to-vector-to-authorized-retrieval flow, Qdrant role, failure handling and three interview answers. | M31: Owner teach-back; no command | N31: Business summary, technical deep-dive, layman analogy, decision recap and interview Q&A completed. | O31: docs/learning/W2-learning-review.md | P31: ADR-002, ADR-003, ADR-006 | Q31: W2-12 | R31: No runtime rollback; revise the learning note through document approval if inaccurate. | S31: Not Started | T31: Mandatory learning gate before Week 3. | U31: Week 2 learning gate after all implementation and checkpoint work. Codex teaches the business outcome and architecture; the owner completes a teach-back and interview practice. No runtime action is permitted. Business value: converts completed work into reusable understanding and decision ownership.
A32: W3-01 | B32: Week 3 | C32: 1 | D32: MUST | E32: LLM contract | F32: Create provider-neutral chat/tool/usage types and fake provider. | G32: RAG logic should not depend on Bedrock response formats. | H32: Codex (code) + User (execute) | I32: 1 | J32: W3-001 | K32: BED-001 | L32: Fake tests cover success, timeout and malformed response. | M32: pytest tests/unit/test_llm_provider.py -q | N32: Normalized errors and usage fields are stable. | O32: docs/test-evidence/W3-01-llm-contract.txt | P32: ADR-002, ADR-004 | Q32: W2-13 | R32: Switch configuration back to fake provider. | S32: Not Started | U32: Week 3 LLM contract task in the end-to-end architecture. After Code Edit Approval, Codex writes only the approved code/configuration/test code for “Create provider-neutral chat/tool/usage types and fake provider.”; you run the verification/deployment commands and return the results. Business value: RAG logic should not depend on Bedrock response formats. Interview focus: explain where this component sits, how it fails safely and how it is rolled back.
A33: W3-02 | B33: Week 3 | C33: 2 | D33: MUST | E33: AWS AI adapter | F33: Implement Bedrock adapter behind marked integration tests. | G33: Bedrock is the primary AWS model boundary without GPU operations. | H33: Codex (code) + User (execute) | I33: 1.25 | J33: W3-001 | K33: AWS-002, BED-001 | L33: Adapter has deadlines/retry caps and no hard-coded model ID. | M33: pytest tests/unit/test_bedrock_adapter.py -q | N33: Offline tests pass; live test is skipped unless explicitly enabled. | O33: docs/test-evidence/W3-02-bedrock.txt | P33: ADR-004 | Q33: W3-01 | R33: Set LLM_PROVIDER=fake; revoke test session if created. | S33: Not Started | U33: Week 3 AWS AI adapter task in the end-to-end architecture. After Code Edit Approval, Codex writes only the approved code/configuration/test code for “Implement Bedrock adapter behind marked integration tests.”; you run the verification/deployment commands and return the results. Business value: Bedrock is the primary AWS model boundary without GPU operations. Interview focus: explain where this component sits, how it fails safely and how it is rolled back.
A34: W3-03 | B34: Week 3 | C34: 3 | D34: MUST | E34: Prompt boundary | F34: Create versioned evidence-bound prompt template. | G34: Retrieved documents are data, never instructions. | H34: Codex (code) + User (execute) | I34: 0.75 | J34: W3-001 | K34: None | L34: Prompt clearly delimits evidence and demands citations/abstention. | M34: pytest tests/unit/test_prompt_template.py -q | N34: Injection fixture cannot override system policy. | O34: docs/test-evidence/W3-03-prompt.txt | P34: ADR-006, ADR-017 | Q34: W3-01 | R34: Restore previous approved prompt version. | S34: Not Started | U34: Week 3 Prompt boundary task in the end-to-end architecture. After Code Edit Approval, Codex writes only the approved code/configuration/test code for “Create versioned evidence-bound prompt template.”; you run the verification/deployment commands and return the results. Business value: Retrieved documents are data, never instructions. Interview focus: explain where this component sits, how it fails safely and how it is rolled back.
A35: W3-04 | B35: Week 3 | C35: 4 | D35: MUST | E35: RAG pipeline | F35: Authorize, retrieve, grade, generate and validate citations. | G35: This is the core safe-answer path. | H35: Codex (code) + User (execute) | I35: 1.5 | J35: W3-001 | K35: RAG-001 | L35: Structured Answer contains only supplied source IDs. | M35: pytest tests/unit/test_rag_pipeline.py -q | N35: Good evidence answers; low evidence abstains. | O35: docs/test-evidence/W3-04-rag.txt | P35: ADR-006, ADR-017 | Q35: W3-01:W3-03,W2-09 | R35: Switch to last-known-good prompt/model/retriever configuration. | S35: Not Started | U35: Week 3 RAG pipeline task in the end-to-end architecture. After Code Edit Approval, Codex writes only the approved code/configuration/test code for “Authorize, retrieve, grade, generate and validate citations.”; you run the verification/deployment commands and return the results. Business value: This is the core safe-answer path. Interview focus: explain where this component sits, how it fails safely and how it is rolled back.
A36: W3-05 | B36: Week 3 | C36: 5 | D36: MUST | E36: Guardrails | F36: Add deterministic input/output/citation safety checks. | G36: Deterministic policy must surround probabilistic generation. | H36: Codex (code) + User (execute) | I36: 1 | J36: W3-003 | K36: SEC-001, DATA-002 | L36: Malformed, unauthorized and uncited outputs fail safely. | M36: pytest tests/security tests/unit/test_guardrails.py -q | N36: Security suite passes with redacted logs. | O36: docs/test-evidence/W3-05-guardrails.txt | P36: ADR-006 | Q36: W3-04 | R36: Disable affected model route and return safe refusal. | S36: Not Started | U36: Week 3 Guardrails task in the end-to-end architecture. After Code Edit Approval, Codex writes only the approved code/configuration/test code for “Add deterministic input/output/citation safety checks.”; you run the verification/deployment commands and return the results. Business value: Deterministic policy must surround probabilistic generation. Interview focus: explain where this component sits, how it fails safely and how it is rolled back.
A37: W3-06 | B37: Week 3 | C37: 6 | D37: MUST | E37: Evaluation data | F37: Create 25+ golden cases with sources, facts, tenant and safety tags. | G37: Quality thresholds require versioned, representative truth data. | H37: User | I37: 1.25 | J37: W3-002 | K37: EVAL-001, DATA-001 | L37: Dataset passes schema and privacy review. | M37: python tools/validate_eval_dataset.py configs/eval/golden.jsonl | N37: 25+ valid cases; no prohibited data. | O37: docs/test-evidence/W3-06-golden.txt | P37: ADR-017 | Q37: W2-09 | R37: Revert dataset version; never silently edit expected answers. | S37: Not Started | U37: Week 3 owner decision/checkpoint in Evaluation data. You choose, approve or execute “Create 25+ golden cases with sources, facts, tenant and safety tags.” because the decision affects downstream architecture and risk. Codex explains alternatives and may draft approved wording only under the proper approval stage. Business value: Quality thresholds require versioned, representative truth data. Interview focus: explain the decision, trade-off and downstream consequence.
A38: W3-07 | B38: Week 3 | C38: 7 | D38: MUST | E38: Evaluation harness | F38: Measure retrieval, citations, abstention, latency and cost. | G38: Promotion must rely on repeatable evidence, not a demo. | H38: Codex (code) + User (execute) | I38: 1.5 | J38: W3-002 | K38: EVAL-001 | L38: Baseline report and nonzero regression exit behavior exist. | M38: python -m enterprise_ai.evaluation.run --dataset configs/eval/golden.jsonl --out reports/eval.json | N38: Recall@5, citation precision, groundedness, latency and estimated cost recorded. | O38: reports/eval.json | P38: ADR-017 | Q38: W3-04,W3-06 | R38: Restore last approved baseline; block release on unresolved regression. | S38: Not Started | U38: Week 3 Evaluation harness task in the end-to-end architecture. After Code Edit Approval, Codex writes only the approved code/configuration/test code for “Measure retrieval, citations, abstention, latency and cost.”; you run the verification/deployment commands and return the results. Business value: Promotion must rely on repeatable evidence, not a demo. Interview focus: explain where this component sits, how it fails safely and how it is rolled back.
A39: W3-08 | B39: Week 3 | C39: 8 | D39: MUST | E39: Security testing | F39: Test injection, cross-tenant retrieval, unsafe output and logging redaction. | G39: RAG expands the attack surface through untrusted content. | H39: Codex (code) + User (execute) | I39: 1 | J39: W3-003 | K39: SEC-001 | L39: All adversarial fixtures fail safely. | M39: pytest tests/security -q | N39: No unauthorized chunk/action; no raw content in logs. | O39: docs/test-evidence/W3-08-security.txt | P39: ADR-006 | Q39: W3-05 | R39: Disable affected path; purge/re-index poisoned test document. | S39: Not Started | U39: Week 3 Security testing task in the end-to-end architecture. After Code Edit Approval, Codex writes only the approved code/configuration/test code for “Test injection, cross-tenant retrieval, unsafe output and logging redaction.”; you run the verification/deployment commands and return the results. Business value: RAG expands the attack surface through untrusted content. Interview focus: explain where this component sits, how it fails safely and how it is rolled back.
A40: W3-09 | B40: Week 3 | C40: 9 | D40: MUST | E40: Telemetry | F40: Record retrieval/model/token/guardrail metrics without content. | G40: Stage-level data explains latency, errors and cost. | H40: Codex (code) + User (execute) | I40: 0.75 | J40: W4-003 | K40: OBS-001 | L40: Metrics include versions/outcomes and exclude prompt/document text. | M40: pytest tests/unit/test_telemetry.py -q | N40: Redaction tests pass; metrics names are documented. | O40: docs/test-evidence/W3-09-telemetry.txt | P40: ADR-008 | Q40: W3-04 | R40: Disable exporter or revert instrumentation, not core answer path. | S40: Not Started | U40: Week 3 Telemetry task in the end-to-end architecture. After Code Edit Approval, Codex writes only the approved code/configuration/test code for “Record retrieval/model/token/guardrail metrics without content.”; you run the verification/deployment commands and return the results. Business value: Stage-level data explains latency, errors and cost. Interview focus: explain where this component sits, how it fails safely and how it is rolled back.
A41: W3-10 | B41: Week 3 | C41: 10 | D41: MUST | E41: Regression gate | F41: Set initial thresholds: Recall@5 >=0.85 and citation-valid/safe-abstain >=95%. | G41: Thresholds convert evaluation into a release decision. | H41: User (execute) + Codex (guide/code) | I41: 0.75 | J41: W3-002 | K41: SLO-001 | L41: CI-style command fails on a material regression. | M41: make evaluate | N41: Baseline passes; synthetic regression fails. | O41: docs/test-evidence/W3-10-gate.txt | P41: ADR-017 | Q41: W3-07 | R41: Revert candidate prompt/model/index and preserve failing evidence. | S41: Not Started | U41: Week 3 Regression gate task in the end-to-end architecture. After Code Edit Approval, Codex writes only the approved code/configuration/test code for “Set initial thresholds: Recall@5 >=0.85 and citation-valid/safe-abstain >=95%.”; you run the verification/deployment commands and return the results. Business value: Thresholds convert evaluation into a release decision. Interview focus: explain where this component sits, how it fails safely and how it is rolled back.
A42: W3-11 | B42: Week 3 | C42: 11 | D42: MUST | E42: Rollback drill | F42: Restore prior prompt/model/retriever/index configuration and re-evaluate. | G42: RAG changes can regress without application code changes. | H42: User (execute) + Codex (guide/code) | I42: 1 | J42: W3-ROLLBACK-001 | K42: None | L42: Last-known-good configuration returns baseline results. | M42: make rollback-rag && make evaluate | N42: Rollback record identifies versions and post-rollback metrics. | O42: docs/rollback-records/W3-rag.md | P42: ADR-012 | Q42: W3-10 | R42: Forward-fix only after a new feature cycle. | S42: Not Started | U42: Week 3 Rollback drill task in the end-to-end architecture. After Code Edit Approval, Codex writes only the approved code/configuration/test code for “Restore prior prompt/model/retriever/index configuration and re-evaluate.”; you run the verification/deployment commands and return the results. Business value: RAG changes can regress without application code changes. Interview focus: explain where this component sits, how it fails safely and how it is rolled back.
A43: W3-12 | B43: Week 3 | C43: 12 | D43: MUST | E43: Checkpoint | F43: Approve cited RAG and quality gate before adding agent behavior. | G43: Agent tools should not be added to an ungrounded answer system. | H43: User | I43: 0.75 | J43: W3-REVIEW-001 | K43: APP-001 | L43: Grounded answer or abstention works; security/regression/rollback tests pass. | M43: make test && make evaluate | N43: Owner sign-off and unresolved metrics documented. | O43: docs/deployment-records/W3-signoff.md | P43: ADR-016 | Q43: W3-01:W3-11 | R43: Keep agent endpoints disabled until approved. | S43: Not Started | U43: Week 3 business/decision documentation task in Checkpoint. The owner provides or approves the facts; after Document Writing Approval, Codex may draft only the approved business-first documentation. No code or command execution is permitted. Business value: Agent tools should not be added to an ungrounded answer system. Interview focus: explain the decision, its alternatives and downstream impact.
A44: W3-13 | B44: Week 3 | C44: 13 | D44: MUST | E44: Weekly learning | F44: Complete the Week 3 cited-RAG business, architecture and interview teach-back. | G44: Builds confidence explaining grounded answers, abstention, evaluation and model-provider boundaries. | H44: User (execute) + Codex (guide/code) | I44: 1 | J44: WEEKLY-LEARN-001 | K44: None | L44: Owner explains cited RAG, guardrails, evaluation thresholds, rollback and three interview answers. | M44: Owner teach-back; no command | N44: Business summary, technical deep-dive, layman analogy, decision recap and interview Q&A completed. | O44: docs/learning/W3-learning-review.md | P44: ADR-004 and Week 3 ADRs | Q44: W3-12 | R44: No runtime rollback; revise the learning note through document approval if inaccurate. | S44: Not Started | T44: Mandatory learning gate before Week 4. | U44: Week 3 learning gate after all implementation and checkpoint work. Codex teaches the business outcome and architecture; the owner completes a teach-back and interview practice. No runtime action is permitted. Business value: converts completed work into reusable understanding and decision ownership.
A45: W4-01 | B45: Week 4 | C45: 1 | D45: MUST | E45: API | F45: Implement health, query and agent endpoints using dependency interfaces. | G45: A thin typed boundary isolates clients from implementation details. | H45: Codex (code) + User (execute) | I45: 1.5 | J45: W4-001 | K45: SEC-001 | L45: Endpoints return normalized schemas and request IDs. | M45: pytest tests/unit/test_api.py -q | N45: Health and fake query tests pass; no internal prompt/error leak. | O45: docs/test-evidence/W4-01-api.txt | P45: ADR-007 | Q45: W3-13 | R45: Roll back image/config and disable new route. | S45: Not Started | U45: Week 4 API task in the end-to-end architecture. After Code Edit Approval, Codex writes only the approved code/configuration/test code for “Implement health, query and agent endpoints using dependency interfaces.”; you run the verification/deployment commands and return the results. Business value: A thin typed boundary isolates clients from implementation details. Interview focus: explain where this component sits, how it fails safely and how it is rolled back.
A46: W4-02 | B46: Week 4 | C46: 2 | D46: MUST | E46: Authorization | F46: Implement auth context interface and deny before retrieval/action. | G46: Identity and authorization are deterministic platform controls. | H46: Codex (code) + User (execute) | I46: 1 | J46: W4-001 | K46: SEC-001 | L46: Unauthorized query never invokes retriever or tool. | M46: pytest tests/security/test_api_authorization.py -q | N46: Mock call assertions prove deny-before-retrieve. | O46: docs/test-evidence/W4-02-auth.txt | P46: ADR-006 | Q46: W4-01 | R46: Disable endpoint or restore previous auth dependency. | S46: Not Started | U46: Week 4 Authorization task in the end-to-end architecture. After Code Edit Approval, Codex writes only the approved code/configuration/test code for “Implement auth context interface and deny before retrieval/action.”; you run the verification/deployment commands and return the results. Business value: Identity and authorization are deterministic platform controls. Interview focus: explain where this component sits, how it fails safely and how it is rolled back.
A47: W4-03 | B47: Week 4 | C47: 3 | D47: MUST | E47: Agent state | F47: Define typed LangGraph state, explicit nodes and terminal outcomes. | G47: Agents are bounded workflows, not autonomous black boxes. | H47: Codex (code) + User (execute) | I47: 1.25 | J47: W4-002 | K47: APP-001 | L47: Every path reaches answer, denied, rejected, timed-out or safe-terminal. | M47: pytest tests/unit/test_agent_graph.py -q | N47: Graph routing tests pass; Mermaid matches implementation. | O47: docs/test-evidence/W4-03-graph.txt | P47: ADR-005 | Q47: W4-02 | R47: Feature flag disables graph; query endpoint remains read-only. | S47: Not Started | U47: Week 4 Agent state task in the end-to-end architecture. After Code Edit Approval, Codex writes only the approved code/configuration/test code for “Define typed LangGraph state, explicit nodes and terminal outcomes.”; you run the verification/deployment commands and return the results. Business value: Agents are bounded workflows, not autonomous black boxes. Interview focus: explain where this component sits, how it fails safely and how it is rolled back.
A48: W4-04 | B48: Week 4 | C48: 4 | D48: MUST | E48: Tools | F48: Add one read-only status tool with narrow schema. | G48: Read-only tool proves integration at low consequence. | H48: Codex (code) + User (execute) | I48: 0.75 | J48: W4-002 | K48: None | L48: Allowlist and JSON schema reject malformed calls. | M48: pytest tests/unit/test_agent_tools.py -q | N48: Only allowlisted tool executes; output is normalized/redacted. | O48: docs/test-evidence/W4-04-read-tool.txt | P48: ADR-005 | Q48: W4-03 | R48: Remove tool registration and restore prior graph. | S48: Not Started | U48: Week 4 Tools task in the end-to-end architecture. After Code Edit Approval, Codex writes only the approved code/configuration/test code for “Add one read-only status tool with narrow schema.”; you run the verification/deployment commands and return the results. Business value: Read-only tool proves integration at low consequence. Interview focus: explain where this component sits, how it fails safely and how it is rolled back.
A49: W4-05 | B49: Week 4 | C49: 5 | D49: MUST | E49: Human approval | F49: Add mocked write tool that requires durable approval. | G49: Consequential actions cannot rely on model intent. | H49: Codex (code) + User (execute) | I49: 1.25 | J49: W4-002 | K49: APP-001 | L49: No approval/rejection/expired approval prevents execution. | M49: pytest tests/security/test_agent_approval.py -q | N49: 100% write executions have valid approval and idempotency key. | O49: docs/test-evidence/W4-05-approval.txt | P49: ADR-005, ADR-006 | Q49: W4-03,W4-04 | R49: Disable write-tool feature flag and invalidate pending approvals. | S49: Not Started | U49: Week 4 Human approval task in the end-to-end architecture. After Code Edit Approval, Codex writes only the approved code/configuration/test code for “Add mocked write tool that requires durable approval.”; you run the verification/deployment commands and return the results. Business value: Consequential actions cannot rely on model intent. Interview focus: explain where this component sits, how it fails safely and how it is rolled back.
A50: W4-06 | B50: Week 4 | C50: 6 | D50: MUST | E50: Budgets | F50: Enforce step, tool-call, token/time deadline and retry limits. | G50: Bounds prevent loops, retry storms and unplanned model spend. | H50: Codex (code) + User (execute) | I50: 1 | J50: W4-002 | K50: COST-001 | L50: Budget-exceeded paths stop safely and record reason. | M50: pytest tests/unit/test_agent_budgets.py -q | N50: No repeated tool execution; timeouts are bounded. | O50: docs/test-evidence/W4-06-budgets.txt | P50: ADR-005 | Q50: W4-03 | R50: Reduce limits or disable agent route. | S50: Not Started | U50: Week 4 Budgets task in the end-to-end architecture. After Code Edit Approval, Codex writes only the approved code/configuration/test code for “Enforce step, tool-call, token/time deadline and retry limits.”; you run the verification/deployment commands and return the results. Business value: Bounds prevent loops, retry storms and unplanned model spend. Interview focus: explain where this component sits, how it fails safely and how it is rolled back.
A51: W4-07 | B51: Week 4 | C51: 7 | D51: MUST | E51: State security | F51: Persist only redacted agent state and audit decisions. | G51: Checkpoints must not become a secret/PII store. | H51: Codex (code) + User (execute) | I51: 0.75 | J51: W4-002 | K51: RET-001 | L51: State fixture contains IDs/outcomes but no content/secrets. | M51: pytest tests/security/test_agent_state_redaction.py -q | N51: Redaction assertion passes. | O51: docs/test-evidence/W4-07-state.txt | P51: ADR-006 | Q51: W4-05 | R51: Purge test checkpoints and restore safe serializer. | S51: Not Started | U51: Week 4 State security task in the end-to-end architecture. After Code Edit Approval, Codex writes only the approved code/configuration/test code for “Persist only redacted agent state and audit decisions.”; you run the verification/deployment commands and return the results. Business value: Checkpoints must not become a secret/PII store. Interview focus: explain where this component sits, how it fails safely and how it is rolled back.
A52: W4-08 | B52: Week 4 | C52: 8 | D52: MUST | E52: Observability | F52: Trace API to retrieval, LLM, guardrail, approval and tool. | G52: Correlated traces make probabilistic workflows diagnosable. | H52: Codex (code) + User (execute) | I52: 1 | J52: W4-003 | K52: OBS-001 | L52: One local trace contains all stages and safe attributes. | M52: pytest tests/feature/test_trace_correlation.py -q | N52: Trace ID links JSON logs and spans; content is redacted. | O52: docs/test-evidence/W4-08-trace.json | P52: ADR-008 | Q52: W4-01:W4-07 | R52: Disable exporter; preserve local logs and core service. | S52: Not Started | U52: Week 4 Observability task in the end-to-end architecture. After Code Edit Approval, Codex writes only the approved code/configuration/test code for “Trace API to retrieval, LLM, guardrail, approval and tool.”; you run the verification/deployment commands and return the results. Business value: Correlated traces make probabilistic workflows diagnosable. Interview focus: explain where this component sits, how it fails safely and how it is rolled back.
A53: W4-09 | B53: Week 4 | C53: 9 | D53: MUST | E53: Failure testing | F53: Exercise denial, malformed args, injection, timeout, loop and rejection. | G53: Agent safety is proven through negative paths. | H53: Codex (code) + User (execute) | I53: 1 | J53: W4-002 | K53: None | L53: All failure modes terminate without write side effects. | M53: pytest tests/security/test_agent_* tests/feature/test_agent_failures.py -q | N53: Audit records show safe terminal reason. | O53: docs/test-evidence/W4-09-failures.txt | P53: ADR-005, ADR-017 | Q53: W4-05:W4-08 | R53: Disable agent endpoint and preserve evidence. | S53: Not Started | U53: Week 4 Failure testing task in the end-to-end architecture. After Code Edit Approval, Codex writes only the approved code/configuration/test code for “Exercise denial, malformed args, injection, timeout, loop and rejection.”; you run the verification/deployment commands and return the results. Business value: Agent safety is proven through negative paths. Interview focus: explain where this component sits, how it fails safely and how it is rolled back.
A54: W4-10 | B54: Week 4 | C54: 10 | D54: SHOULD | E54: Performance | F54: Run bounded local smoke/load test with fake/approved model. | G54: Concurrency and timeouts must fail predictably before EKS. | H54: Codex (code) + User (execute) | I54: 0.75 | J54: W4-001 | K54: COST-001 | L54: No unbounded queue; p95/p99 baseline is recorded. | M54: pytest tests/feature/test_api_load_smoke.py -q | N54: Latency/error/concurrency report is redacted. | O54: docs/test-evidence/W4-10-load.json | P54: ADR-007, ADR-008 | Q54: W4-01,W4-06 | R54: Reduce traffic; revert concurrency settings. | S54: Not Started | U54: Week 4 Performance task in the end-to-end architecture. After Code Edit Approval, Codex writes only the approved code/configuration/test code for “Run bounded local smoke/load test with fake/approved model.”; you run the verification/deployment commands and return the results. Business value: Concurrency and timeouts must fail predictably before EKS. Interview focus: explain where this component sits, how it fails safely and how it is rolled back.
A55: W4-11 | B55: Week 4 | C55: 11 | D55: MUST | E55: Release rollback | F55: Deploy local immutable version N+1, force regression and restore N. | G55: Release rollback is separate from infrastructure rollback. | H55: User (execute) + Codex (guide/code) | I55: 1 | J55: W4-ROLLBACK-001 | K55: None | L55: N becomes healthy and passes feature tests after rollback. | M55: make rollback-release && make smoke | N55: Rollback duration and health evidence recorded. | O55: docs/rollback-records/W4-release.md | P55: ADR-012 | Q55: W4-01:W4-10 | R55: Keep agent route disabled until the failure is fixed. | S55: Not Started | U55: Week 4 Release rollback task in the end-to-end architecture. After Code Edit Approval, Codex writes only the approved code/configuration/test code for “Deploy local immutable version N+1, force regression and restore N.”; you run the verification/deployment commands and return the results. Business value: Release rollback is separate from infrastructure rollback. Interview focus: explain where this component sits, how it fails safely and how it is rolled back.
A56: W4-12 | B56: Week 4 | C56: 12 | D56: MUST | E56: Checkpoint | F56: Approve controlled API/agent and Week 5 AWS inputs. | G56: Cloud infrastructure should not be planned for an unsafe runtime. | H56: User | I56: 0.75 | J56: W4-REVIEW-001 | K56: AWS-001, AWS-002, NET-001, TAG-001, COST-001 | L56: All consequential actions are policy-valid and approved. | M56: make test && make security-scan | N56: Owner signs graph, API, evidence and rollback record. | O56: docs/deployment-records/W4-signoff.md | P56: ADR-016 | Q56: W4-01:W4-11 | R56: Do not begin Terraform plan until inputs and cost ceiling are approved. | S56: Not Started | U56: Week 4 business/decision documentation task in Checkpoint. The owner provides or approves the facts; after Document Writing Approval, Codex may draft only the approved business-first documentation. No code or command execution is permitted. Business value: Cloud infrastructure should not be planned for an unsafe runtime. Interview focus: explain the decision, its alternatives and downstream impact.
A57: W4-13 | B57: Week 4 | C57: 13 | D57: MUST | E57: Weekly learning | F57: Complete the Week 4 API/agent business, architecture and interview teach-back. | G57: Makes bounded agents, human approval, API controls and observability explainable to business and technical interviewers. | H57: User (execute) + Codex (guide/code) | I57: 1 | J57: WEEKLY-LEARN-001 | K57: None | L57: Owner explains API boundaries, authorization, agent state/budgets, human approval, telemetry and three interview answers. | M57: Owner teach-back; no command | N57: Business summary, technical deep-dive, layman analogy, decision recap and interview Q&A completed. | O57: docs/learning/W4-learning-review.md | P57: ADR-005, ADR-007 and Week 4 ADRs | Q57: W4-12 | R57: No runtime rollback; revise the learning note through document approval if inaccurate. | S57: Not Started | T57: Mandatory learning gate before Week 5. | U57: Week 4 learning gate after all implementation and checkpoint work. Codex teaches the business outcome and architecture; the owner completes a teach-back and interview practice. No runtime action is permitted. Business value: converts completed work into reusable understanding and decision ownership.
A58: W5-01 | B58: Week 5 | C58: 1 | D58: MUST | E58: AWS inputs | F58: Confirm sandbox account, region, network, tags, data residency and budget ceiling. | G58: Terraform cannot be safely reviewed with ambiguous ownership or cost. | H58: User | I58: 1 | J58: W5-INPUTS-001 | K58: AWS-001, AWS-002, NET-001, TAG-001, COST-001, PRIV-001 | L58: All variables are non-secret and approved. | M58: Review infra/environments/sandbox/terraform.tfvars.example | N58: No credential/secret value is requested. | O58: docs/cost-estimates/W5-inputs.md | P58: ADR-010, ADR-011 | Q58: W4-13 | R58: Do not initialize/apply until inputs are approved. | S58: Not Started | U58: Week 5 business/decision documentation task in AWS inputs. The owner provides or approves the facts; after Document Writing Approval, Codex may draft only the approved business-first documentation. No code or command execution is permitted. Business value: Terraform cannot be safely reviewed with ambiguous ownership or cost. Interview focus: explain the decision, its alternatives and downstream impact.
A59: W5-02 | B59: Week 5 | C59: 2 | D59: MUST | E59: State bootstrap | F59: Build isolated encrypted/versioned S3 state and Terraform 1.5 DynamoDB locking stack. | G59: State must survive platform rollback and be removed last during full teardown. | H59: Codex (code) + User (execute) | I59: 1.25 | J59: W5-001 | K59: AWS-001, AWS-002, TAG-001 | L59: fmt/validate/Checkov pass; apply remains manual. | M59: terraform -chdir=infra/bootstrap fmt -check && terraform -chdir=infra/bootstrap validate | N59: Bootstrap plan contains only expected resources. | O59: docs/test-evidence/W5-02-bootstrap.txt | P59: ADR-009 | Q59: W5-01 | R59: Destroy platform first; bootstrap destroy is separately reviewed. | S59: Not Started | U59: Week 5 State bootstrap task in the end-to-end architecture. After Code Edit Approval, Codex writes only the approved code/configuration/test code for “Build isolated encrypted/versioned S3 state and Terraform 1.5 DynamoDB locking stack.”; you run the verification/deployment commands and return the results. Business value: State must survive platform rollback and be removed last during full teardown. Interview focus: explain where this component sits, how it fails safely and how it is rolled back.
A60: W5-03 | B60: Week 5 | C60: 3 | D60: MUST | E60: Security foundation | F60: Create KMS, private/versioned S3 and secret-metadata modules. | G60: Encryption and secret separation are foundational controls. | H60: Codex (code) + User (execute) | I60: 1.25 | J60: W5-001 | K60: KMS-001, TAG-001 | L60: No public access or secret value resource exists. | M60: terraform -chdir=infra/environments/sandbox validate && checkov -d infra/modules | N60: Security controls pass; deletion settings are explicit. | O60: docs/test-evidence/W5-03-security.txt | P60: ADR-009, ADR-014 | Q60: W5-01,W5-02 | R60: Apply prior Terraform version; use purge only for disposable sandbox. | S60: Not Started | U60: Week 5 Security foundation task in the end-to-end architecture. After Code Edit Approval, Codex writes only the approved code/configuration/test code for “Create KMS, private/versioned S3 and secret-metadata modules.”; you run the verification/deployment commands and return the results. Business value: Encryption and secret separation are foundational controls. Interview focus: explain where this component sits, how it fails safely and how it is rolled back.
A61: W5-04 | B61: Week 5 | C61: 4 | D61: MUST | E61: IAM | F61: Create least-privilege runtime, ingestion and GitHub OIDC roles. | G61: Workloads need short-lived, separated permissions. | H61: Codex (code) + User (execute) | I61: 1.25 | J61: W5-001 | K61: GHA-001, BED-001, TAG-001 | L61: No wildcard action/resource without reviewed exception. | M61: checkov -d infra && opa test policies/opa -v | N61: Trust policies bind approved repo/environment and workload identity. | O61: docs/test-evidence/W5-04-iam.txt | P61: ADR-006, ADR-010 | Q61: W5-01 | R61: Disable role session/restore prior policy; do not store keys. | S61: Not Started | U61: Week 5 IAM task in the end-to-end architecture. After Code Edit Approval, Codex writes only the approved code/configuration/test code for “Create least-privilege runtime, ingestion and GitHub OIDC roles.”; you run the verification/deployment commands and return the results. Business value: Workloads need short-lived, separated permissions. Interview focus: explain where this component sits, how it fails safely and how it is rolled back.
A62: W5-05 | B62: Week 5 | C62: 5 | D62: MUST | E62: AWS retrieval | F62: Create private encrypted OpenSearch and ECR modules. | G62: OpenSearch is the AWS vector target; ECR stores immutable images. | H62: Codex (code) + User (execute) | I62: 1.5 | J62: W5-001 | K62: NET-001, TAG-001 | L62: Private network, TLS, encryption, logs and access controls are planned. | M62: terraform -chdir=infra/environments/sandbox plan -out=tfplan | N62: Plan summary shows only expected resources and estimated baseline cost. | O62: docs/test-evidence/W5-05-platform-plan.txt | P62: ADR-003, ADR-015 | Q62: W5-03,W5-04 | R62: Apply reviewed previous Terraform version or destroy disposable resources in order. | S62: Not Started | U62: Week 5 AWS retrieval task in the end-to-end architecture. After Code Edit Approval, Codex writes only the approved code/configuration/test code for “Create private encrypted OpenSearch and ECR modules.”; you run the verification/deployment commands and return the results. Business value: OpenSearch is the AWS vector target; ECR stores immutable images. Interview focus: explain where this component sits, how it fails safely and how it is rolled back.
A63: W5-06 | B63: Week 5 | C63: 6 | D63: MUST | E63: Policy as code | F63: Implement OPA and Checkov security/tagging policies with fixtures. | G63: Policy gates make critical architecture decisions executable. | H63: Codex (code) + User (execute) | I63: 1 | J63: W5-003 | K63: AWS-002, TAG-001 | L63: Insecure fixtures fail; secure fixtures pass. | M63: opa test policies/opa -v && checkov -d infra | N63: Failures identify resource/rule/remediation. | O63: docs/test-evidence/W5-06-policy.txt | P63: ADR-010, ADR-017 | Q63: W5-03:W5-05 | R63: Revert candidate policy only through reviewed exception/ADR. | S63: Not Started | U63: Week 5 Policy as code task in the end-to-end architecture. After Code Edit Approval, Codex writes only the approved code/configuration/test code for “Implement OPA and Checkov security/tagging policies with fixtures.”; you run the verification/deployment commands and return the results. Business value: Policy gates make critical architecture decisions executable. Interview focus: explain where this component sits, how it fails safely and how it is rolled back.
A64: W5-07 | B64: Week 5 | C64: 7 | D64: MUST | E64: CI/CD | F64: Create PR CI and Terraform-plan workflow using GitHub OIDC. | G64: Automated gates and short-lived identity reduce change and credential risk. | H64: Codex (code) + User (execute) | I64: 1.5 | J64: W5-002 | K64: GHA-001 | L64: All required checks run; apply/destroy are owner-gated. | M64: Review .github/workflows and run actionlint if available | N64: No access-key secret; immutable action pins are TODO/approved. | O64: docs/test-evidence/W5-07-ci.txt | P64: ADR-010, ADR-011 | Q64: W5-04,W5-06 | R64: Disable workflow; revoke OIDC trust; keep last good release. | S64: Not Started | U64: Week 5 CI/CD task in the end-to-end architecture. After Code Edit Approval, Codex writes only the approved code/configuration/test code for “Create PR CI and Terraform-plan workflow using GitHub OIDC.”; you run the verification/deployment commands and return the results. Business value: Automated gates and short-lived identity reduce change and credential risk. Interview focus: explain where this component sits, how it fails safely and how it is rolled back.
A65: W5-08 | B65: Week 5 | C65: 8 | D65: MUST | E65: Supply chain | F65: Build image, scan with Trivy/Grype and generate Syft SBOM. | G65: Deployment must use a known, scanned immutable artifact. | H65: Codex (code) + User (execute) | I65: 1 | J65: W5-002 | K65: None | L65: Critical findings fail per policy and SBOM is retained. | M65: docker build -t enterprise-ai:test . && trivy image enterprise-ai:test | N65: Redacted scan reports and SPDX/CycloneDX SBOM exist. | O65: docs/test-evidence/W5-08-supply-chain.txt | P65: ADR-017 | Q65: W5-07 | R65: Do not publish vulnerable digest; restore prior approved digest. | S65: Not Started | U65: Week 5 Supply chain task in the end-to-end architecture. After Code Edit Approval, Codex writes only the approved code/configuration/test code for “Build image, scan with Trivy/Grype and generate Syft SBOM.”; you run the verification/deployment commands and return the results. Business value: Deployment must use a known, scanned immutable artifact. Interview focus: explain where this component sits, how it fails safely and how it is rolled back.
A66: W5-09 | B66: Week 5 | C66: 9 | D66: MUST | E66: Plan review | F66: Generate saved Terraform plan, JSON policy result and human-readable summary. | G66: Applying the reviewed bytes prevents unseen infrastructure change. | H66: User (execute) + Codex (guide/code) | I66: 1 | J66: W5-004 | K66: COST-001 | L66: Plan, policy and cost review are approved before any apply. | M66: make plan-sandbox | N66: Summary lists creates/updates/deletes, costs and residual risks. | O66: docs/deployment-records/W5-plan-review.md | P66: ADR-010, ADR-011 | Q66: W5-02:W5-08 | R66: Discard saved plan on code/input drift and regenerate. | S66: Not Started | U66: Week 5 Plan review task in the end-to-end architecture. After Code Edit Approval, Codex writes only the approved code/configuration/test code for “Generate saved Terraform plan, JSON policy result and human-readable summary.”; you run the verification/deployment commands and return the results. Business value: Applying the reviewed bytes prevents unseen infrastructure change. Interview focus: explain where this component sits, how it fails safely and how it is rolled back.
A67: W5-10 | B67: Week 5 | C67: 10 | D67: MUST | E67: Sandbox lifecycle | F67: After explicit approval, deploy/validate/rollback/destroy in controlled sequence. | G67: Capability must be proven, but Codex must never self-approve mutations. | H67: User | I67: 1.5 | J67: W5-004 | K67: DEST-001 | L67: Reviewed plan applies; validation passes; rollback path is recorded. | M67: make deploy-sandbox # owner-approved only | N67: Deployment record contains plan hash, approver, resources and health. | O67: docs/deployment-records/W5-sandbox.md | P67: ADR-012 | Q67: W5-09 | R67: Use last-known-good Terraform version; destroy is not ordinary rollback. | S67: Not Started | U67: Week 5 owner decision/checkpoint in Sandbox lifecycle. You choose, approve or execute “After explicit approval, deploy/validate/rollback/destroy in controlled sequence.” because the decision affects downstream architecture and risk. Codex explains alternatives and may draft approved wording only under the proper approval stage. Business value: Capability must be proven, but Codex must never self-approve mutations. Interview focus: explain the decision, trade-off and downstream consequence.
A68: W5-11 | B68: Week 5 | C68: 11 | D68: MUST | E68: Teardown plan | F68: Create and review platform destroy plan; preserve bootstrap until platform is gone. | G68: Deletion order prevents dependency residue and loss of auditability. | H68: User (execute) + Codex (guide/code) | I68: 0.75 | J68: W5-004 | K68: DEST-001 | L68: Destroy plan targets only approved sandbox resources. | M68: make plan-destroy-sandbox | N68: Plan and deletion order approved; KMS window noted. | O68: docs/deployment-records/W5-destroy-plan.md | P68: ADR-009, ADR-012 | Q68: W5-10 | R68: Cancel before apply if any unexpected target appears. | S68: Not Started | U68: Week 5 Teardown plan task in the end-to-end architecture. After Code Edit Approval, Codex writes only the approved code/configuration/test code for “Create and review platform destroy plan; preserve bootstrap until platform is gone.”; you run the verification/deployment commands and return the results. Business value: Deletion order prevents dependency residue and loss of auditability. Interview focus: explain where this component sits, how it fails safely and how it is rolled back.
A69: W5-12 | B69: Week 5 | C69: 12 | D69: MUST | E69: Cleanliness proof | F69: Run verify-clean using required tags and native service APIs after approved teardown. | G69: A successful Terraform destroy is not proof of zero residual resources. | H69: User (execute) + Codex (guide/code) | I69: 1 | J69: W5-004 | K69: TAG-001, KMS-001 | L69: No active unmanaged resource remains; exception is documented PendingDeletion KMS key. | M69: make destroy-sandbox && make verify-clean # owner-approved only | N69: Resource-cleanliness report is complete and signed. | O69: docs/resource-cleanliness/W5-report.json | P69: ADR-013, ADR-014 | Q69: W5-11 | R69: Remove residuals in dependency order; do not delete bootstrap until clean. | S69: Not Started | U69: Week 5 Cleanliness proof task in the end-to-end architecture. After Code Edit Approval, Codex writes only the approved code/configuration/test code for “Run verify-clean using required tags and native service APIs after approved teardown.”; you run the verification/deployment commands and return the results. Business value: A successful Terraform destroy is not proof of zero residual resources. Interview focus: explain where this component sits, how it fails safely and how it is rolled back.
A70: W5-13 | B70: Week 5 | C70: 13 | D70: MUST | E70: Checkpoint | F70: Approve AWS lifecycle evidence and Week 6 EKS deployment inputs. | G70: Runtime deployment should use only reviewed, reconstructable platform components. | H70: User | I70: 0.75 | J70: W5-REVIEW-001 | K70: EKS-001, OBS-001, SLO-001 | L70: Plans/policies/scans/lifecycle evidence pass; no plaintext secret or unmanaged resource. | M70: Review W5 evidence index | N70: Owner sign-off and any deferred actual deployment clearly recorded. | O70: docs/deployment-records/W5-signoff.md | P70: ADR-016 | Q70: W5-01:W5-12 | R70: Do not deploy EKS app until the platform gate passes. | S70: Not Started | U70: Week 5 business/decision documentation task in Checkpoint. The owner provides or approves the facts; after Document Writing Approval, Codex may draft only the approved business-first documentation. No code or command execution is permitted. Business value: Runtime deployment should use only reviewed, reconstructable platform components. Interview focus: explain the decision, its alternatives and downstream impact.
A71: W5-14 | B71: Week 5 | C71: 14 | D71: MUST | E71: Weekly learning | F71: Complete the Week 5 AWS lifecycle business, architecture and interview teach-back. | G71: Connects infrastructure-as-code, identity, policy, supply chain, cost and teardown into a controlled cloud story. | H71: User (execute) + Codex (guide/code) | I71: 1 | J71: WEEKLY-LEARN-001 | K71: None | L71: Owner explains reviewed plans, OIDC, policy gates, immutable artifacts, rollback/teardown and three interview answers. | M71: Owner teach-back; no command | N71: Business summary, technical deep-dive, layman analogy, decision recap and interview Q&A completed. | O71: docs/learning/W5-learning-review.md | P71: Week 5 ADRs | Q71: W5-13 | R71: No runtime rollback; revise the learning note through document approval if inaccurate. | S71: Not Started | T71: Mandatory learning gate before Week 6. | U71: Week 5 learning gate after all implementation and checkpoint work. Codex teaches the business outcome and architecture; the owner completes a teach-back and interview practice. No runtime action is permitted. Business value: converts completed work into reusable understanding and decision ownership.
A72: W6-01 | B72: Week 6 | C72: 1 | D72: MUST | E72: Artifact promotion | F72: Publish scanned image to ECR by immutable digest. | G72: Rollback and provenance require immutable deployment identity. | H72: User (execute) + Codex (guide/code) | I72: 0.75 | J72: W5-002 | K72: EKS-001 | L72: Digest matches the scanned/SBOM artifact. | M72: docker inspect --format='{{index .RepoDigests 0}}' enterprise-ai:test | N72: Digest, scan and SBOM are linked in deployment record. | O72: docs/deployment-records/W6-image.md | P72: ADR-012, ADR-017 | Q72: W5-14 | R72: Restore prior approved digest; never reuse a mutable tag as authority. | S72: Not Started | U72: Week 6 Artifact promotion task in the end-to-end architecture. After Code Edit Approval, Codex writes only the approved code/configuration/test code for “Publish scanned image to ECR by immutable digest.”; you run the verification/deployment commands and return the results. Business value: Rollback and provenance require immutable deployment identity. Interview focus: explain where this component sits, how it fails safely and how it is rolled back.
A73: W6-02 | B73: Week 6 | C73: 2 | D73: MUST | E73: Kubernetes | F73: Create EKS deployment/Service with non-root/read-only settings and probes. | G73: Production-shaped runtime boundaries reduce container and availability risk. | H73: Codex (code) + User (execute) | I73: 1.5 | J73: W6-001 | K73: EKS-001 | L73: Server dry-run and policy validation pass. | M73: kubectl apply --dry-run=server -f deploy/k8s | N73: Manifests use immutable digest and no secret literal. | O73: docs/test-evidence/W6-02-k8s.txt | P73: ADR-015 | Q73: W6-01 | R73: kubectl rollout undo or redeploy previous digest. | S73: Not Started | U73: Week 6 Kubernetes task in the end-to-end architecture. After Code Edit Approval, Codex writes only the approved code/configuration/test code for “Create EKS deployment/Service with non-root/read-only settings and probes.”; you run the verification/deployment commands and return the results. Business value: Production-shaped runtime boundaries reduce container and availability risk. Interview focus: explain where this component sits, how it fails safely and how it is rolled back.
A74: W6-03 | B74: Week 6 | C74: 3 | D74: MUST | E74: Workload identity | F74: Configure EKS Pod Identity/IRSA, RBAC and least-privilege service account. | G74: Pods must never contain static AWS credentials. | H74: Codex (code) + User (execute) | I74: 1 | J74: W6-001 | K74: AWS-001, EKS-001 | L74: Pod accesses only required AWS APIs and env has no static key. | M74: kubectl exec deploy/enterprise-ai-api -- env | grep AWS_ACCESS_KEY_ID; test $? -ne 0 | N74: No static credential; role session is short-lived and scoped. | O74: docs/test-evidence/W6-03-identity.txt | P74: ADR-006 | Q74: W5-04,W6-02 | R74: Remove service-account binding and restore prior role policy. | S74: Not Started | U74: Week 6 Workload identity task in the end-to-end architecture. After Code Edit Approval, Codex writes only the approved code/configuration/test code for “Configure EKS Pod Identity/IRSA, RBAC and least-privilege service account.”; you run the verification/deployment commands and return the results. Business value: Pods must never contain static AWS credentials. Interview focus: explain where this component sits, how it fails safely and how it is rolled back.
A75: W6-04 | B75: Week 6 | C75: 4 | D75: MUST | E75: Network security | F75: Apply NetworkPolicy and approved ingress/egress boundaries. | G75: Retrieval/model paths should be explicit and least privilege. | H75: Codex (code) + User (execute) | I75: 1 | J75: W6-001 | K75: NET-001, EKS-001 | L75: Denied destination test fails; approved dependencies remain reachable. | M75: kubectl apply --dry-run=server -f deploy/k8s/networkpolicy.yaml | N75: Network test evidence documents permitted flows. | O75: docs/test-evidence/W6-04-network.txt | P75: ADR-006, ADR-015 | Q75: W6-03 | R75: Restore last-known-good policy; scale down if isolation is uncertain. | S75: Not Started | U75: Week 6 Network security task in the end-to-end architecture. After Code Edit Approval, Codex writes only the approved code/configuration/test code for “Apply NetworkPolicy and approved ingress/egress boundaries.”; you run the verification/deployment commands and return the results. Business value: Retrieval/model paths should be explicit and least privilege. Interview focus: explain where this component sits, how it fails safely and how it is rolled back.
A76: W6-05 | B76: Week 6 | C76: 5 | D76: MUST | E76: Resilience | F76: Configure requests/limits, HPA, PDB and rolling update settings. | G76: Availability and autoscaling must be defined before load/chaos tests. | H76: Codex (code) + User (execute) | I76: 1 | J76: W6-001 | K76: SLO-001 | L76: Schema/policy checks pass and settings have rationale. | M76: kubectl apply --dry-run=server -f deploy/k8s | N76: PDB/HPA do not conflict at minimum replicas. | O76: docs/test-evidence/W6-05-resilience.txt | P76: ADR-015 | Q76: W6-02 | R76: Rollback manifests and return to last safe replica/settings. | S76: Not Started | U76: Week 6 Resilience task in the end-to-end architecture. After Code Edit Approval, Codex writes only the approved code/configuration/test code for “Configure requests/limits, HPA, PDB and rolling update settings.”; you run the verification/deployment commands and return the results. Business value: Availability and autoscaling must be defined before load/chaos tests. Interview focus: explain where this component sits, how it fails safely and how it is rolled back.
A77: W6-06 | B77: Week 6 | C77: 6 | D77: MUST | E77: Observability platform | F77: Deploy OTel path to CloudWatch/X-Ray plus Prometheus/Grafana/Jaeger option. | G77: Vendor-neutral telemetry supports both AWS and open-source operations. | H77: Codex (code) + User (execute) | I77: 1.25 | J77: W6-002 | K77: OBS-001 | L77: One request trace links API, retrieval and LLM spans. | M77: pytest tests/feature/test_trace_correlation.py -q | N77: Trace/log/metric IDs correlate without sensitive content. | O77: docs/test-evidence/W6-06-observability.json | P77: ADR-008 | Q77: W4-08,W6-02 | R77: Disable broken exporter; preserve local telemetry path. | S77: Not Started | U77: Week 6 Observability platform task in the end-to-end architecture. After Code Edit Approval, Codex writes only the approved code/configuration/test code for “Deploy OTel path to CloudWatch/X-Ray plus Prometheus/Grafana/Jaeger option.”; you run the verification/deployment commands and return the results. Business value: Vendor-neutral telemetry supports both AWS and open-source operations. Interview focus: explain where this component sits, how it fails safely and how it is rolled back.
A78: W6-07 | B78: Week 6 | C78: 7 | D78: MUST | E78: SRE objectives | F78: Approve SLIs/SLOs, error-budget policy and burn alerts. | G78: Reliability targets must reflect user pain and govern releases. | H78: User (execute) + Codex (guide/code) | I78: 1 | J78: W6-002 | K78: SLO-001, OBS-001 | L78: Availability 99.9%, p95<4s, p99<10s, retrieval p99<750ms, grounded>=95%, isolation/safety=100% are reviewed. | M78: promtool check rules observability/alerts.yml | N78: Rules validate and map to an owner/runbook. | O78: docs/architecture/slo.md | P78: ADR-017 | Q78: W6-06 | R78: Disable noisy alert only through reviewed threshold/runbook update. | S78: Not Started | U78: Week 6 SRE objectives task in the end-to-end architecture. After Code Edit Approval, Codex writes only the approved code/configuration/test code for “Approve SLIs/SLOs, error-budget policy and burn alerts.”; you run the verification/deployment commands and return the results. Business value: Reliability targets must reflect user pain and govern releases. Interview focus: explain where this component sits, how it fails safely and how it is rolled back.
A79: W6-08 | B79: Week 6 | C79: 8 | D79: MUST | E79: Runbook | F79: Create and rehearse inference-latency-spike runbook. | G79: An alert is useful only if it drives a safe action. | H79: Codex + User | I79: 1 | J79: W6-002 | K79: OBS-001 | L79: Runbook covers impact, stabilize, stage isolation, rollback and evidence. | M79: Run tabletop and record timeline | N79: Owner can distinguish retrieval, model, queue and dependency latency. | O79: runbooks/inference-latency.md | P79: ADR-008, ADR-012 | Q79: W6-06,W6-07 | R79: Rollback release/config; use safe refusal/fallback if approved. | S79: Not Started | U79: Week 6 Runbook task in the end-to-end architecture. After Code Edit Approval, Codex writes only the approved code/configuration/test code for “Create and rehearse inference-latency-spike runbook.”; you run the verification/deployment commands and return the results. Business value: An alert is useful only if it drives a safe action. Interview focus: explain where this component sits, how it fails safely and how it is rolled back.
A80: W6-09 | B80: Week 6 | C80: 9 | D80: MUST | E80: Failure/chaos | F80: Stop Qdrant/inject LLM timeout locally; prepare FIS plan without executing it. | G80: Controlled failure proves readiness, bounded retries and alert/runbook quality. | H80: User (execute) + Codex (guide/code) | I80: 1 | J80: W6-002 | K80: FIS-001 | L80: Readiness fails, no retry storm, alert/runbook activates; FIS has tag targets/stop alarms. | M80: pytest tests/feature/test_failure_modes.py -q | N80: RTO and alert evidence recorded; no production target. | O80: docs/test-evidence/W6-09-chaos.txt | P80: ADR-017 | Q80: W6-07,W6-08 | R80: Stop experiment, restore dependency, rollback configuration. | S80: Not Started | U80: Week 6 Failure/chaos task in the end-to-end architecture. After Code Edit Approval, Codex writes only the approved code/configuration/test code for “Stop Qdrant/inject LLM timeout locally; prepare FIS plan without executing it.”; you run the verification/deployment commands and return the results. Business value: Controlled failure proves readiness, bounded retries and alert/runbook quality. Interview focus: explain where this component sits, how it fails safely and how it is rolled back.
A81: W6-10 | B81: Week 6 | C81: 10 | D81: MUST | E81: End-to-end validation | F81: Run local and sandbox cited query plus golden evaluation/security suite. | G81: Final proof must combine functionality, quality, security and observability. | H81: User (execute) + Codex (guide/code) | I81: 1.25 | J81: W6-003 | K81: EVAL-001 | L81: No material regression; sandbox query has citations and trace ID. | M81: make final-proof | N81: Evidence index links tests, eval, scans, traces and decisions. | O81: docs/test-evidence/W6-final-index.md | P81: ADR-017 | Q81: W6-01:W6-09 | R81: Block promotion and restore last-known-good release/config. | S81: Not Started | U81: Week 6 End-to-end validation task in the end-to-end architecture. After Code Edit Approval, Codex writes only the approved code/configuration/test code for “Run local and sandbox cited query plus golden evaluation/security suite.”; you run the verification/deployment commands and return the results. Business value: Final proof must combine functionality, quality, security and observability. Interview focus: explain where this component sits, how it fails safely and how it is rolled back.
A82: W6-11 | B82: Week 6 | C82: 11 | D82: MUST | E82: Release rollback drill | F82: Force a safe sandbox regression and restore previous image/configuration. | G82: Rollback must be timed and revalidated before handover. | H82: User | I82: 0.75 | J82: W6-003 | K82: DEST-001 | L82: Last-known-good release passes health, smoke and evaluation gates. | M82: make rollback-release && make validate-sandbox | N82: Rollback record includes trigger, approver, duration and post-checks. | O82: docs/rollback-records/W6-release.md | P82: ADR-012 | Q82: W6-10 | R82: Keep failed digest blocked; open defect with evidence. | S82: Not Started | U82: Week 6 owner decision/checkpoint in Release rollback drill. You choose, approve or execute “Force a safe sandbox regression and restore previous image/configuration.” because the decision affects downstream architecture and risk. Codex explains alternatives and may draft approved wording only under the proper approval stage. Business value: Rollback must be timed and revalidated before handover. Interview focus: explain the decision, trade-off and downstream consequence.
A83: W6-12 | B83: Week 6 | C83: 12 | D83: MUST | E83: Full teardown | F83: Run approved destroy sequence, remove bootstrap last and verify cleanliness. | G83: Learning-project cost and residue must stop after use. | H83: User | I83: 1.25 | J83: W5-004 | K83: DEST-001, KMS-001 | L83: No active project resource remains; KMS exception is PendingDeletion only. | M83: make plan-destroy-sandbox; owner approve; make destroy-sandbox; make verify-clean | N83: Signed cleanup report and deletion record exist. | O83: docs/resource-cleanliness/W6-final.json | P83: ADR-009, ADR-013, ADR-014 | Q83: W6-11 | R83: Remove residuals in dependency order; never broadly target unverified resources. | S83: Not Started | U83: Week 6 owner decision/checkpoint in Full teardown. You choose, approve or execute “Run approved destroy sequence, remove bootstrap last and verify cleanliness.” because the decision affects downstream architecture and risk. Codex explains alternatives and may draft approved wording only under the proper approval stage. Business value: Learning-project cost and residue must stop after use. Interview focus: explain the decision, trade-off and downstream consequence.
A84: W6-13 | B84: Week 6 | C84: 13 | D84: MUST | E84: Handover and learning | F84: Update ADRs with actual outcomes and deliver a 10-minute architecture explanation. | G84: The engineer must understand and defend every decision, not just run generated code. | H84: User | I84: 1 | J84: W6-003 | K84: None | L84: Explain objective, flows, security, evaluation, agent controls, SLOs and reversibility. | M84: Owner presentation rehearsal and final workbook review | N84: All TODOs/deferrals are visible; source-of-truth and workbook agree. | O84: docs/architecture/final-review.md | P84: ADR-016 | Q84: W6-01:W6-12 | R84: Any future change starts a new controlled feature cycle. | S84: Not Started | U84: Week 6 owner decision/checkpoint in Handover and learning. You choose, approve or execute “Update ADRs with actual outcomes and deliver a 10-minute architecture explanation.” because the decision affects downstream architecture and risk. Codex explains alternatives and may draft approved wording only under the proper approval stage. Business value: The engineer must understand and defend every decision, not just run generated code. Interview focus: explain the decision, trade-off and downstream consequence.
A85: W6-14 | B85: Week 6 | C85: 14 | D85: MUST | E85: Weekly learning | F85: Complete the Week 6 end-to-end architecture, deployment, SRE and interview teach-back. | G85: Consolidates the full enterprise AI platform into a deployment, reliability, security and business-value narrative. | H85: User (execute) + Codex (guide/code) | I85: 1.5 | J85: WEEKLY-LEARN-001 | K85: None | L85: Owner delivers a 10-minute end-to-end explanation plus failure, rollback, teardown and five interview answers. | M85: Owner teach-back; no command | N85: Final business case, architecture deep-dive, layman walkthrough, decision recap and interview Q&A completed. | O85: docs/learning/W6-learning-review.md | P85: All approved ADRs | Q85: W6-13 | R85: No runtime rollback; revise the learning note through document approval if inaccurate. | S85: Not Started | T85: Final learning and interview-readiness gate. | U85: Week 6 learning gate after all implementation and checkpoint work. Codex teaches the business outcome and architecture; the owner completes a teach-back and interview practice. No runtime action is permitted. Business value: converts completed work into reusable understanding and decision ownership.

Sheet 03 W1 Control Foundation
A1: Week 1 — Control Foundation
A2: Control foundation: repo, traceability, test/security gates, separated Terraform roots and cleanup-verifier skeleton.
A4: Progress | D4: Blocked | G4: Exit gate
A5: =IF(COUNTA(O10:O40)=0,0,COUNTIF(O10:O40,"Done")/COUNTA(A10:A40)) -> 0.56521739 | D5: =COUNTIF(O10:O40,"Blocked") -> 0 | G5: Preflight, tests, reviewed-plan and cleanup workflows are understood and pass before RAG code.
A9: Step ID | B9: Seq | C9: Priority | D9: Workstream | E9: Action | F9: Architecture Reason | G9: Owner | H9: Effort | I9: Prompt | J9: User TODO | K9: Acceptance | L9: Owner Verify | M9: Evidence | N9: Rollback/Teardown | O9: Status | P9: Task Context
A10: W1-01 | B10: 1 | C10: MUST | D10: Scope | E10: Confirm the first use case, user group, exclusions and measurable MVP outcome. | F10: A narrow use case prevents a platform-without-a-problem and sets evaluation truth. | G10: User | H10: 1 | I10: W1-MVP-001 | J10: USE-001, DATA-001, EVAL-001 | K10: One approved one-page scope and 5 representative questions. | L10: Owner review of docs/features/MVP-001.md | M10: docs/features/MVP-001.md | N10: Revert scope file before implementation begins. | O10: Done | P10: Week 1 business/decision documentation task in Scope. The owner provides or approves the facts; after Document Writing Approval, Codex may draft only the approved business-first documentation. No code or command execution is permitted. Business value: A narrow use case prevents a platform-without-a-problem and sets evaluation truth. Interview focus: explain the decision, its alternatives and downstream impact.
A11: W1-02 | B11: 2 | C11: MUST | D11: Governance | E11: Record source precedence: v1.1 controls override older schedule while preserving technical prompts. | F11: Prevents Codex and coach from following conflicting weekly sequences. | G11: User (execute) + Codex (guide/code) | H11: 0.5 | I11: W1-GOV-001 | J11: None | K11: Decision recorded and referenced by all feature prompts. | L11: Review docs/adr/ADR-000-source-precedence.md | M11: docs/adr/ADR-000-source-precedence.md | N11: Restore prior ADR only through reviewed superseding decision. | O11: Done | P11: Week 1 business/decision documentation task in Governance. The owner provides or approves the facts; after Document Writing Approval, Codex may draft only the approved business-first documentation. No code or command execution is permitted. Business value: Prevents Codex and coach from following conflicting weekly sequences. Interview focus: explain the decision, its alternatives and downstream impact.
A12: W1-03 | B12: 3 | C12: MUST | D12: Repository | E12: Create the monorepo and documentation/evidence structure. | F12: Gives every change an auditable home and supports clean ownership. | G12: Codex (code) + User (execute) | H12: 1.5 | I12: W1-001 | J12: TAG-001 | K12: Required folders, README and Makefile exist. | L12: find . -maxdepth 3 -type d | sort | M12: docs/test-evidence/W1-03-layout.txt | N12: Delete only newly created empty skeleton paths after diff review. | O12: Done | P12: Week 1 Repository task in the end-to-end architecture. After Code Edit Approval, Codex writes only the approved code/configuration/test code for “Create the monorepo and documentation/evidence structure.”; you run the verification/deployment commands and return the results. Business value: Gives every change an auditable home and supports clean ownership. Interview focus: explain where this component sits, how it fails safely and how it is rolled back.
A13: W1-04 | B13: 4 | C13: MUST | D13: Traceability | E13: Create feature-matrix.yaml and the first feature record. | F13: Links purpose, files, tests, cost, approval, rollback and teardown. | G13: Codex (code) + User (execute) | H13: 1 | I13: W1-001 | J13: USE-001, TAG-001 | K13: Schema validates and feature MVP-001 is planned. | L13: python tools/validate_feature_matrix.py | M13: docs/test-evidence/W1-04-feature-matrix.json | N13: Restore previous matrix version from Git. | O13: Done | P13: Week 1 Traceability task in the end-to-end architecture. After Code Edit Approval, Codex writes only the approved code/configuration/test code for “Create feature-matrix.yaml and the first feature record.”; you run the verification/deployment commands and return the results. Business value: Links purpose, files, tests, cost, approval, rollback and teardown. Interview focus: explain where this component sits, how it fails safely and how it is rolled back.
A14: W1-05 | B14: 5 | C14: MUST | D14: Python foundation | E14: Create reproducible dependencies and typed configuration. | F14: Fail-fast configuration and portable dependencies reduce hidden runtime risk. | G14: Codex (code) + User (execute) | H14: 1.5 | I14: W1-002 | J14: AWS-002, BED-001, EMB-001 | K14: pip install succeeds; config tests pass offline. | L14: pip install -r requirements.txt && pytest tests/unit/test_config.py -q | M14: docs/test-evidence/W1-05-config.txt | N14: Revert dependency/config commit and recreate virtual environment. | O14: Done | P14: Week 1 Python foundation task in the end-to-end architecture. After Code Edit Approval, Codex writes only the approved code/configuration/test code for “Create reproducible dependencies and typed configuration.”; you run the verification/deployment commands and return the results. Business value: Fail-fast configuration and portable dependencies reduce hidden runtime risk. Interview focus: explain where this component sits, how it fails safely and how it is rolled back.
A15: W1-06 | B15: 6 | C15: MUST | D15: Testing | E15: Create pytest layers, deterministic fakes and evidence capture. | F15: Testing is a feature gate, not an afterthought. | G15: Codex (code) + User (execute) | H15: 1.25 | I15: W1-003 | J15: None | K15: Markers and sample feature test run locally. | L15: pytest tests/unit tests/feature -q | M15: docs/test-evidence/W1-06-tests.json | N15: Revert test framework commit; no platform resources exist. | O15: Done | P15: Week 1 Testing task in the end-to-end architecture. After Code Edit Approval, Codex writes only the approved code/configuration/test code for “Create pytest layers, deterministic fakes and evidence capture.”; you run the verification/deployment commands and return the results. Business value: Testing is a feature gate, not an afterthought. Interview focus: explain where this component sits, how it fails safely and how it is rolled back.
A16: W1-07 | B16: 7 | C16: MUST | D16: Developer controls | E16: Add Make targets for preflight, test, scan, plan, rollback, destroy-plan and verify-clean. | F16: A single, reviewable command vocabulary keeps user and Codex synchronized. | G16: Codex (code) + User (execute) | H16: 1 | I16: W1-001 | J16: None | K16: Make help documents safe commands; mutating commands are gated. | L16: make help && make preflight | M16: docs/test-evidence/W1-07-make.txt | N16: Revert Makefile changes. | O16: Done | P16: Week 1 Developer controls task in the end-to-end architecture. After Code Edit Approval, Codex writes only the approved code/configuration/test code for “Add Make targets for preflight, test, scan, plan, rollback, destroy-plan and verify-clean.”; you run the verification/deployment commands and return the results. Business value: A single, reviewable command vocabulary keeps user and Codex synchronized. Interview focus: explain where this component sits, how it fails safely and how it is rolled back.
A17: W1-08 | B17: 8 | C17: MUST | D17: DevSecOps | E17: Add pre-commit formatting, linting and secret scanning baseline. | F17: Shift-left checks stop secrets and poor-quality changes before PR. | G17: Codex (code) + User (execute) | H17: 1 | I17: W1-003 | J17: SEC-003 | K17: Insecure secret fixture is blocked without committing a real secret. | L17: pre-commit run --all-files | M17: docs/test-evidence/W1-08-precommit.txt | N17: Revert hooks only after owner review; rotate any accidentally exposed credential. | O17: Done | P17: Week 1 DevSecOps task in the end-to-end architecture. After Code Edit Approval, Codex writes only the approved code/configuration/test code for “Add pre-commit formatting, linting and secret scanning baseline.”; you run the verification/deployment commands and return the results. Business value: Shift-left checks stop secrets and poor-quality changes before PR. Interview focus: explain where this component sits, how it fails safely and how it is rolled back.
A18: W1-09 | B18: 9 | C18: MUST | D18: Terraform lifecycle | E18: Separate infra/bootstrap from infra/environments/sandbox and document state removal last. | F18: A platform cannot fully disappear if its state backend is embedded in the same lifecycle. | G18: Codex (code) + User (execute) | H18: 1.25 | I18: W1-004 | J18: AWS-001, AWS-002, TAG-001 | K18: Two roots validate as skeletons and dependency order is documented. | L18: terraform -chdir=infra/bootstrap fmt -check && terraform -chdir=infra/environments/sandbox fmt -check | M18: docs/test-evidence/W1-09-roots.txt | N18: Revert Terraform skeleton; no state exists yet. | O18: Done | P18: Week 1 Terraform lifecycle task in the end-to-end architecture. After Code Edit Approval, Codex writes only the approved code/configuration/test code for “Separate infra/bootstrap from infra/environments/sandbox and document state removal last.”; you run the verification/deployment commands and return the results. Business value: A platform cannot fully disappear if its state backend is embedded in the same lifecycle. Interview focus: explain where this component sits, how it fails safely and how it is rolled back.
A19: W1-10 | B19: 10 | C19: MUST | D19: Reversibility | E19: Create platformctl command contracts with dry-run and approvals. | F19: Deploy, rollback and teardown need distinct safe semantics. | G19: Codex (code) + User (execute) | H19: 1.5 | I19: W1-004 | J19: DEST-001, KMS-001 | K19: CLI help and unit tests prove confirmation/approval gates. | L19: python -m tools.platformctl --help && pytest tests/unit/test_platformctl.py -q | M19: docs/test-evidence/W1-10-platformctl.txt | N19: Revert CLI commit; no cloud mutation is allowed. | O19: Done | P19: Week 1 Reversibility task in the end-to-end architecture. After Code Edit Approval, Codex writes only the approved code/configuration/test code for “Create platformctl command contracts with dry-run and approvals.”; you run the verification/deployment commands and return the results. Business value: Deploy, rollback and teardown need distinct safe semantics. Interview focus: explain where this component sits, how it fails safely and how it is rolled back.
A20: W1-11 | B20: 11 | C20: MUST | D20: Cleanup verification | E20: Implement mocked tag and service-specific residual checks. | F20: Tag-only discovery misses some resources; native checks close the gap. | G20: Codex (code) + User (execute) | H20: 1 | I20: W1-004 | J20: TAG-001, KMS-001 | K20: Mock orphan makes verify-clean fail; PendingDeletion key is documented exception. | L20: pytest tests/teardown -q | M20: docs/test-evidence/W1-11-cleanup.json | N20: Revert verifier implementation; keep the control requirement. | O20: Done | P20: Week 1 Cleanup verification task in the end-to-end architecture. After Code Edit Approval, Codex writes only the approved code/configuration/test code for “Implement mocked tag and service-specific residual checks.”; you run the verification/deployment commands and return the results. Business value: Tag-only discovery misses some resources; native checks close the gap. Interview focus: explain where this component sits, how it fails safely and how it is rolled back.
A21: W1-12 | B21: 12 | C21: MUST | D21: Checkpoint | E21: Review diffs, architecture decisions, test evidence and Week 2 readiness. | F21: Owner approval is the stop point between features/weeks. | G21: User | H21: 1 | I21: W1-REVIEW-001 | J21: All Week 1 TODOs | K21: Every MUST step is Done; no blocker or unapproved scope remains. | L21: make preflight && make test | M21: docs/deployment-records/W1-signoff.md | N21: No Week 2 prompt is used until gaps are resolved. | O21: Done | P21: Week 1 business/decision documentation task in Checkpoint. The owner provides or approves the facts; after Document Writing Approval, Codex may draft only the approved business-first documentation. No code or command execution is permitted. Business value: Owner approval is the stop point between features/weeks. Interview focus: explain the decision, its alternatives and downstream impact.
A22: W1-13 | B22: 13 | C22: MUST | D22: Weekly learning | E22: Complete the Week 1 business, architecture and interview teach-back. | F22: Turns governance, repository, test and lifecycle controls into an explainable architecture story. | G22: User (execute) + Codex (guide/code) | H22: 1 | I22: WEEKLY-LEARN-001 | J22: None | K22: Owner explains the Week 1 business outcome, control flow, decisions, failure boundaries and three interview answers without reading code. | L22: Owner teach-back; no command | M22: docs/learning/W1-learning-review.md | N22: No runtime rollback; revise the learning note through document approval if inaccurate. | O22: Done | P22: Week 1 learning gate after all implementation and checkpoint work. Codex teaches the business outcome and architecture; the owner completes a teach-back and interview practice. No runtime action is permitted. Business value: converts completed work into reusable understanding and decision ownership.
A24: Grouped prompt sequence — full Main / Code Edit / Document Writing / Final Approval prompts are in 10 Codex Prompts
A25: Order | B25: Prompt ID | C25: Feature | D25: Purpose | E25: Required Inputs | F25: Expected Outputs | G25: Example Usage
A26: 1 | B26: W1-MVP-001 | C26: MVP scope and approval record | D26: Create the missing one-page MVP-001 source-of-truth artifact before repository implementation. | E26: USE-001, DATA-001 and five starter EVAL-001 questions; no credentials | F26: docs/features/MVP-001.md with scope, exclusions, measures and approval fields | G26: Review Main Prompt → Column M document approval → owner review → Column N final approval
A27: 2 | B27: W1-GOV-001 | C27: Source precedence ADR | D27: Create the missing governance decision without creating unrelated Codex context files. | E27: Source of Truth v1.1 and Coaching Blueprint as read-only references; no credentials | F27: docs/adr/ADR-000-source-precedence.md in Proposed state | G27: Review Main Prompt → Column M document approval → owner review → Column N final approval
A28: 3 | B28: W1-001 | C28: Repository and feature-control foundation | D28: Create the traceability and evidence structure before feature code. | E28: TODO_REPOSITORY, TODO_USER_OR_TEAM, TODO_COST_CENTER | F28: Monorepo skeleton, feature-matrix.yaml, ADR/test/evidence folders, Makefile, README | G28: Review Main Prompt → Column L code approval → owner runs TEST-001 guidance → Column M documents → Column N final approval
A29: 4 | B29: W1-002 | C29: Dependency and configuration foundation | D29: Make installation reproducible and configuration explicit. | E29: Python 3.11; no cloud credentials | F29: requirements*.txt, pyproject.toml, .env.example, typed config and unit tests | G29: Review Main Prompt → Column L code approval → owner runs TEST-001 guidance → Column M documents → Column N final approval
A30: 5 | B30: W1-003 | C30: Test and evidence framework | D30: Make every acceptance criterion executable and auditable. | E30: Feature template and repo skeleton | F30: pytest markers, fixtures, evidence naming rules, sample feature test | G30: Review Main Prompt → Column L code approval → owner runs TEST-001 guidance → Column M documents → Column N final approval
A31: 6 | B31: W1-004 | C31: Lifecycle controller and cleanup-verifier skeleton | D31: Treat deployability and reversibility as platform features. | E31: Required tag schema; sandbox-only scope | F31: platformctl commands, dry-run workflows, mocked residual-resource tests | G31: Review Main Prompt → Column L code approval → owner runs TEST-001 guidance → Column M documents → Column N final approval
A32: 7 | B32: W1-REVIEW-001 | C32: Reusable weekly checkpoint | D32: Stop between weeks until MUST work, evidence, decisions, TODOs and rollback readiness are reviewed. | E32: Week 1 sheet, evidence register, ADRs, TODOs and owner-supplied results | F32: docs/deployment-records/W1-signoff.md | G32: Review Main Prompt → Column M document approval → owner review → Column N final approval
A33: 8 | B33: WEEKLY-LEARN-001 | C33: Week 1 owner learning and interview teach-back | D33: Teach the completed week's business outcome, architecture, decisions, trade-offs and failure/rollback story. | E33: Completed weekly tasks, owner-executed results, approved decisions and documentation | F33: Owner teach-back and optional docs/learning/W1-learning-review.md | G33: Use after all weekly work and final approvals; no code or runtime action

Sheet 04 W2 Local Retrieval
A1: Week 2 — Local Retrieval
A2: Local searchable knowledge: typed contracts, secure ingestion, local embeddings, Qdrant, authorization and reversible feature proof.
A4: Progress | D4: Blocked | G4: Exit gate
A5: =IF(COUNTA(O10:O40)=0,0,COUNTIF(O10:O40,"Done")/COUNTA(A10:A40)) -> 0.22727273 | D5: =COUNTIF(O10:O40,"Blocked") -> 0 | G5: Local retrieval deploys, returns authorized expected sources, rolls back and removes without residue.
A9: Step ID | B9: Seq | C9: Priority | D9: Workstream | E9: Action | F9: Architecture Reason | G9: Owner | H9: Effort | I9: Prompt | J9: User TODO | K9: Acceptance | L9: Owner Verify | M9: Evidence | N9: Rollback/Teardown | O9: Status | P9: Task Context
A10: W2-01 | B10: 1 | C10: MUST | D10: Data contracts | E10: Implement provider-neutral document, chunk, query, answer and citation models. | F10: Stable domain types make vector and LLM backends replaceable. | G10: Codex (code) + User (execute) | H10: 1 | I10: W2-001 | J10: DATA-002, SEC-001 | K10: Models validate required identity/classification metadata. | L10: pytest tests/unit/test_models.py -q | M10: docs/test-evidence/W2-01-models.txt | N10: Revert model commit; no stored vectors affected. | O10: Done | P10: Week 2 Data contracts task in the end-to-end architecture. After Code Edit Approval, Codex writes only the approved code/configuration/test code for “Implement provider-neutral document, chunk, query, answer and citation models.”; you run the verification/deployment commands and return the results. Business value: Stable domain types make vector and LLM backends replaceable. Interview focus: explain where this component sits, how it fails safely and how it is rolled back.
A11: W2-02 | B11: 2 | C11: MUST | D11: Vector interface | E11: Define VectorStore protocol and in-memory fake with contract tests. | F11: Business logic must not depend on Qdrant/OpenSearch SDK objects. | G11: Codex (code) + User (execute) | H11: 1.25 | I11: W2-001 | J11: None | K11: Fake passes all contract tests. | L11: pytest tests/contract/test_vector_store.py -q | M11: docs/test-evidence/W2-02-vector-contract.txt | N11: Revert interface only before downstream adapters merge. | O11: Done | P11: Week 2 Vector interface task in the end-to-end architecture. After Code Edit Approval, Codex writes only the approved code/configuration/test code for “Define VectorStore protocol and in-memory fake with contract tests.”; you run the verification/deployment commands and return the results. Business value: Business logic must not depend on Qdrant/OpenSearch SDK objects. Interview focus: explain where this component sits, how it fails safely and how it is rolled back.
A12: W2-03 | B12: 3 | C12: MUST | D12: Local platform | E12: Start pinned Qdrant through Docker Compose with healthcheck. | F12: A real client/server vector store gives useful local integration evidence. | G12: Codex (code) + User (execute) | H12: 1 | I12: W2-001 | J12: None | K12: Qdrant becomes healthy without an embedded credential. | L12: docker compose up -d qdrant && docker compose ps | M12: docs/test-evidence/W2-03-qdrant.txt | N12: docker compose down -v; verify no project volume/network. | O12: Done | P12: Week 2 Local platform task in the end-to-end architecture. After Code Edit Approval, Codex writes only the approved code/configuration/test code for “Start pinned Qdrant through Docker Compose with healthcheck.”; you run the verification/deployment commands and return the results. Business value: A real client/server vector store gives useful local integration evidence. Interview focus: explain where this component sits, how it fails safely and how it is rolled back.
A13: W2-04 | B13: 4 | C13: MUST | D13: Vector adapters | E13: Implement Qdrant adapter and OpenSearch adapter boundary. | F13: Local and AWS retrieval must satisfy the same contract. | G13: Codex (code) + User (execute) | H13: 1.5 | I13: W2-001 | J13: AWS-002, NET-001 | K13: Fake/Qdrant tests pass; AWS tests remain marked/skipped. | L13: pytest tests/contract tests/integration/test_qdrant.py -q | M13: docs/test-evidence/W2-04-adapters.txt | N13: Delete test collection and restore previous adapter version. | O13: Done | P13: Week 2 Vector adapters task in the end-to-end architecture. After Code Edit Approval, Codex writes only the approved code/configuration/test code for “Implement Qdrant adapter and OpenSearch adapter boundary.”; you run the verification/deployment commands and return the results. Business value: Local and AWS retrieval must satisfy the same contract. Interview focus: explain where this component sits, how it fails safely and how it is rolled back.
A14: W2-05 | B14: 5 | C14: MUST | D14: Embeddings | E14: Implement sentence-transformer and deterministic fake embedders. | F14: Local CPU embeddings avoid a paid dependency while preserving provider exit. | G14: Codex (code) + User (execute) | H14: 1.25 | I14: W2-002 | J14: EMB-001 | K14: Batch, normalization and dimension mismatch tests pass. | L14: pytest tests/unit/test_embedder.py -q | M14: docs/test-evidence/W2-05-embedder.txt | N14: Restore previous model configuration and recreate collection if dimension changed. | O14: Not Started | P14: Week 2 Embeddings task in the end-to-end architecture. After Code Edit Approval, Codex writes only the approved code/configuration/test code for “Implement sentence-transformer and deterministic fake embedders.”; you run the verification/deployment commands and return the results. Business value: Local CPU embeddings avoid a paid dependency while preserving provider exit. Interview focus: explain where this component sits, how it fails safely and how it is rolled back.
A15: W2-06 | B15: 6 | C15: MUST | D15: Ingestion | E15: Implement validation, hashing, normalization and deterministic token chunking. | F15: Reproducible chunk IDs/versioning make re-index and deletion safe. | G15: Codex (code) + User (execute) | H15: 1.5 | I15: W2-003 | J15: DATA-001, DATA-002 | K15: Same input produces same IDs; changed version is distinguishable. | L15: pytest tests/unit/test_chunking.py tests/unit/test_ingestion.py -q | M15: docs/test-evidence/W2-06-ingestion.txt | N15: Delete affected document version and re-ingest last approved manifest. | O15: Not Started | P15: Week 2 Ingestion task in the end-to-end architecture. After Code Edit Approval, Codex writes only the approved code/configuration/test code for “Implement validation, hashing, normalization and deterministic token chunking.”; you run the verification/deployment commands and return the results. Business value: Reproducible chunk IDs/versioning make re-index and deletion safe. Interview focus: explain where this component sits, how it fails safely and how it is rolled back.
A16: W2-07 | B16: 7 | C16: MUST | D16: Privacy | E16: Add replaceable Presidio PII detection/redaction hook. | F16: PII handling belongs before indexing and telemetry. | G16: Codex (code) + User (execute) | H16: 1 | I16: W2-003 | J16: DATA-003 | K16: Configured PII is redacted/quarantined and never appears in evidence logs. | L16: pytest tests/security/test_pii.py -q | M16: docs/test-evidence/W2-07-pii.txt | N16: Delete derived chunks; restore approved unredacted source only in controlled location. | O16: Not Started | P16: Week 2 Privacy task in the end-to-end architecture. After Code Edit Approval, Codex writes only the approved code/configuration/test code for “Add replaceable Presidio PII detection/redaction hook.”; you run the verification/deployment commands and return the results. Business value: PII handling belongs before indexing and telemetry. Interview focus: explain where this component sits, how it fails safely and how it is rolled back.
A17: W2-08 | B17: 8 | C17: MUST | D17: Authorization | E17: Enforce tenant/classification filters before vector search. | F17: The model cannot be trusted to enforce access control. | G17: Codex (code) + User (execute) | H17: 1 | I17: W2-001 | J17: SEC-001 | K17: Cross-tenant query returns zero unauthorized chunks. | L17: pytest tests/security/test_tenant_isolation.py -q | M17: docs/test-evidence/W2-08-isolation.txt | N17: Disable retrieval endpoint and restore last-known-good filter implementation. | O17: Done | P17: Week 2 Authorization task in the end-to-end architecture. After Code Edit Approval, Codex writes only the approved code/configuration/test code for “Enforce tenant/classification filters before vector search.”; you run the verification/deployment commands and return the results. Business value: The model cannot be trusted to enforce access control. Interview focus: explain where this component sits, how it fails safely and how it is rolled back.
A18: W2-09 | B18: 9 | C18: MUST | D18: Feature proof | E18: Ingest approved sample corpus and verify top-5 retrieval. | F18: This is the first measurable RAG foundation outcome. | G18: User (execute) + Codex (guide/code) | H18: 1 | I18: W2-004 | J18: DATA-001, EVAL-001 | K18: Expected source appears in top 5 for representative questions. | L18: python -m enterprise_ai.ingestion.pipeline ingest --source data/sample --tenant demo && pytest tests/feature/test_local_retrieval.py -q | M18: docs/test-evidence/W2-09-retrieval.json | N18: Delete test collection/volume and restore previous config. | O18: Not Started | P18: Week 2 Feature proof task in the end-to-end architecture. After Code Edit Approval, Codex writes only the approved code/configuration/test code for “Ingest approved sample corpus and verify top-5 retrieval.”; you run the verification/deployment commands and return the results. Business value: This is the first measurable RAG foundation outcome. Interview focus: explain where this component sits, how it fails safely and how it is rolled back.
A19: W2-10 | B19: 10 | C19: MUST | D19: Reversibility | E19: Run local deploy, rollback and complete removal drill. | F19: A working feature is incomplete until it can be removed cleanly. | G19: User (execute) + Codex (guide/code) | H19: 1 | I19: W2-004 | J19: DEST-001 | K19: Previous configuration works after rollback; teardown leaves no local residue. | L19: make rollback-local && make destroy-local && make verify-clean-local | M19: docs/rollback-records/W2-local.md | N19: Recreate from pinned Compose/config and re-run feature test. | O19: Not Started | P19: Week 2 Reversibility task in the end-to-end architecture. After Code Edit Approval, Codex writes only the approved code/configuration/test code for “Run local deploy, rollback and complete removal drill.”; you run the verification/deployment commands and return the results. Business value: A working feature is incomplete until it can be removed cleanly. Interview focus: explain where this component sits, how it fails safely and how it is rolled back.
A20: W2-11 | B20: 11 | C20: SHOULD | D20: Learning checkpoint | E20: Explain embeddings, cosine similarity, chunk size/overlap and metadata filtering. | F20: The workbook is also an interview/reference learning plan. | G20: User | H20: 0.75 | I20: W2-LEARN-001 | J20: None | K20: Five-minute explanation uses current implementation evidence. | L20: Record explanation notes in docs/architecture/local-retrieval.md | M20: docs/architecture/local-retrieval.md | N20: Revise ADR/notes; do not change code without a feature cycle. | O20: Not Started | P20: Week 2 owner decision/checkpoint in Learning checkpoint. You choose, approve or execute “Explain embeddings, cosine similarity, chunk size/overlap and metadata filtering.” because the decision affects downstream architecture and risk. Codex explains alternatives and may draft approved wording only under the proper approval stage. Business value: The workbook is also an interview/reference learning plan. Interview focus: explain the decision, trade-off and downstream consequence.
A21: W2-12 | B21: 12 | C21: MUST | D21: Checkpoint | E21: Approve local retrieval gate and Week 3 inputs. | F21: Prevents LLM work from hiding retrieval defects. | G21: User | H21: 0.75 | I21: W2-REVIEW-001 | J21: BED-001, EVAL-001 | K21: All MUST tests and cleanup evidence pass. | L21: make test && make verify-clean-local | M21: docs/deployment-records/W2-signoff.md | N21: Remain on local retrieval until the gate passes. | O21: Not Started | P21: Week 2 business/decision documentation task in Checkpoint. The owner provides or approves the facts; after Document Writing Approval, Codex may draft only the approved business-first documentation. No code or command execution is permitted. Business value: Prevents LLM work from hiding retrieval defects. Interview focus: explain the decision, its alternatives and downstream impact.
A22: W2-13 | B22: 13 | C22: MUST | D22: Weekly learning | E22: Complete the Week 2 local retrieval business, architecture and interview teach-back. | F22: Converts vector retrieval, ingestion, privacy and authorization work into an end-to-end business explanation. | G22: User (execute) + Codex (guide/code) | H22: 1 | I22: WEEKLY-LEARN-001 | J22: None | K22: Owner explains document-to-vector-to-authorized-retrieval flow, Qdrant role, failure handling and three interview answers. | L22: Owner teach-back; no command | M22: docs/learning/W2-learning-review.md | N22: No runtime rollback; revise the learning note through document approval if inaccurate. | O22: Not Started | P22: Week 2 learning gate after all implementation and checkpoint work. Codex teaches the business outcome and architecture; the owner completes a teach-back and interview practice. No runtime action is permitted. Business value: converts completed work into reusable understanding and decision ownership.
A24: Grouped prompt sequence — full Main / Code Edit / Document Writing / Final Approval prompts are in 10 Codex Prompts
A25: Order | B25: Prompt ID | C25: Feature | D25: Purpose | E25: Required Inputs | F25: Expected Outputs | G25: Example Usage
A26: 1 | B26: W2-001 | C26: Domain models and pluggable vector adapters | D26: Prevent vendor SDK types from leaking into RAG logic. | E26: QDRANT_URL; AWS auth only for marked tests | F26: Domain models, VectorStore protocol, Qdrant/OpenSearch/fake adapters, contract tests | G26: Review Main Prompt → Column L code approval → owner runs TEST-001 guidance → Column M documents → Column N final approval
A27: 2 | B27: W2-002 | C27: Embedder contract and local adapter | D27: Support local and future provider embeddings through one boundary. | E27: EMBEDDING_MODEL_ID | F27: Embedder protocol, sentence-transformer/fake adapters, batch and dimension tests | G27: Review Main Prompt → Column L code approval → owner runs TEST-001 guidance → Column M documents → Column N final approval
A28: 3 | B28: W2-003 | C28: Secure ingestion pipeline | D28: Turn approved files into versioned, authorized chunks. | E28: Approved local sample path; tenant/classification rules | F28: Loaders, chunker, Presidio hook, CLI, manifest, quarantine and tests | G28: Review Main Prompt → Column L code approval → owner runs TEST-001 guidance → Column M documents → Column N final approval
A29: 4 | B29: W2-004 | C29: Local Qdrant lifecycle and retrieval proof | D29: Prove the feature can be deployed, tested, rolled back and removed locally. | E29: Docker 24+, QDRANT_URL | F29: docker-compose.yml, local lifecycle targets, integration and cleanup tests | G29: Review Main Prompt → Column L code approval → owner runs TEST-001 guidance → Column M documents → Column N final approval
A30: 5 | B30: W2-LEARN-001 | C30: Local retrieval architecture explanation | D30: Create an interview-ready explanation grounded in the implemented retrieval evidence. | E30: Approved W2 ADRs, adapter/chunking configuration and W2 evidence | F30: docs/architecture/local-retrieval.md | G30: Use only for owner learning and teach-back; no code, command or document mutation
A31: 6 | B31: W2-REVIEW-001 | C31: Reusable weekly checkpoint | D31: Stop between weeks until MUST work, evidence, decisions, TODOs and rollback readiness are reviewed. | E31: Week 2 sheet, evidence register, ADRs, TODOs and owner-supplied results | F31: docs/deployment-records/W2-signoff.md | G31: Review Main Prompt → Column M document approval → owner review → Column N final approval
A32: 7 | B32: WEEKLY-LEARN-001 | C32: Week 2 owner learning and interview teach-back | D32: Teach the completed week's business outcome, architecture, decisions, trade-offs and failure/rollback story. | E32: Completed weekly tasks, owner-executed results, approved decisions and documentation | F32: Owner teach-back and optional docs/learning/W2-learning-review.md | G32: Use after all weekly work and final approvals; no code or runtime action

Sheet 05 W3 Cited RAG
A1: Week 3 — Cited RAG
A2: Cited RAG: provider-neutral LLM, Bedrock adapter, citations/abstention, guardrails, golden evaluation and regression rollback.
A4: Progress | D4: Blocked | G4: Exit gate
A5: =IF(COUNTA(O10:O40)=0,0,COUNTIF(O10:O40,"Done")/COUNTA(A10:A40)) -> 0 | D5: =COUNTIF(O10:O40,"Blocked") -> 0 | G5: A query returns a grounded cited answer or safe abstention; regression/security/rollback tests pass.
A9: Step ID | B9: Seq | C9: Priority | D9: Workstream | E9: Action | F9: Architecture Reason | G9: Owner | H9: Effort | I9: Prompt | J9: User TODO | K9: Acceptance | L9: Owner Verify | M9: Evidence | N9: Rollback/Teardown | O9: Status | P9: Task Context
A10: W3-01 | B10: 1 | C10: MUST | D10: LLM contract | E10: Create provider-neutral chat/tool/usage types and fake provider. | F10: RAG logic should not depend on Bedrock response formats. | G10: Codex (code) + User (execute) | H10: 1 | I10: W3-001 | J10: BED-001 | K10: Fake tests cover success, timeout and malformed response. | L10: pytest tests/unit/test_llm_provider.py -q | M10: docs/test-evidence/W3-01-llm-contract.txt | N10: Switch configuration back to fake provider. | O10: Not Started | P10: Week 3 LLM contract task in the end-to-end architecture. After Code Edit Approval, Codex writes only the approved code/configuration/test code for “Create provider-neutral chat/tool/usage types and fake provider.”; you run the verification/deployment commands and return the results. Business value: RAG logic should not depend on Bedrock response formats. Interview focus: explain where this component sits, how it fails safely and how it is rolled back.
A11: W3-02 | B11: 2 | C11: MUST | D11: AWS AI adapter | E11: Implement Bedrock adapter behind marked integration tests. | F11: Bedrock is the primary AWS model boundary without GPU operations. | G11: Codex (code) + User (execute) | H11: 1.25 | I11: W3-001 | J11: AWS-002, BED-001 | K11: Adapter has deadlines/retry caps and no hard-coded model ID. | L11: pytest tests/unit/test_bedrock_adapter.py -q | M11: docs/test-evidence/W3-02-bedrock.txt | N11: Set LLM_PROVIDER=fake; revoke test session if created. | O11: Not Started | P11: Week 3 AWS AI adapter task in the end-to-end architecture. After Code Edit Approval, Codex writes only the approved code/configuration/test code for “Implement Bedrock adapter behind marked integration tests.”; you run the verification/deployment commands and return the results. Business value: Bedrock is the primary AWS model boundary without GPU operations. Interview focus: explain where this component sits, how it fails safely and how it is rolled back.
A12: W3-03 | B12: 3 | C12: MUST | D12: Prompt boundary | E12: Create versioned evidence-bound prompt template. | F12: Retrieved documents are data, never instructions. | G12: Codex (code) + User (execute) | H12: 0.75 | I12: W3-001 | J12: None | K12: Prompt clearly delimits evidence and demands citations/abstention. | L12: pytest tests/unit/test_prompt_template.py -q | M12: docs/test-evidence/W3-03-prompt.txt | N12: Restore previous approved prompt version. | O12: Not Started | P12: Week 3 Prompt boundary task in the end-to-end architecture. After Code Edit Approval, Codex writes only the approved code/configuration/test code for “Create versioned evidence-bound prompt template.”; you run the verification/deployment commands and return the results. Business value: Retrieved documents are data, never instructions. Interview focus: explain where this component sits, how it fails safely and how it is rolled back.
A13: W3-04 | B13: 4 | C13: MUST | D13: RAG pipeline | E13: Authorize, retrieve, grade, generate and validate citations. | F13: This is the core safe-answer path. | G13: Codex (code) + User (execute) | H13: 1.5 | I13: W3-001 | J13: RAG-001 | K13: Structured Answer contains only supplied source IDs. | L13: pytest tests/unit/test_rag_pipeline.py -q | M13: docs/test-evidence/W3-04-rag.txt | N13: Switch to last-known-good prompt/model/retriever configuration. | O13: Not Started | P13: Week 3 RAG pipeline task in the end-to-end architecture. After Code Edit Approval, Codex writes only the approved code/configuration/test code for “Authorize, retrieve, grade, generate and validate citations.”; you run the verification/deployment commands and return the results. Business value: This is the core safe-answer path. Interview focus: explain where this component sits, how it fails safely and how it is rolled back.
A14: W3-05 | B14: 5 | C14: MUST | D14: Guardrails | E14: Add deterministic input/output/citation safety checks. | F14: Deterministic policy must surround probabilistic generation. | G14: Codex (code) + User (execute) | H14: 1 | I14: W3-003 | J14: SEC-001, DATA-002 | K14: Malformed, unauthorized and uncited outputs fail safely. | L14: pytest tests/security tests/unit/test_guardrails.py -q | M14: docs/test-evidence/W3-05-guardrails.txt | N14: Disable affected model route and return safe refusal. | O14: Not Started | P14: Week 3 Guardrails task in the end-to-end architecture. After Code Edit Approval, Codex writes only the approved code/configuration/test code for “Add deterministic input/output/citation safety checks.”; you run the verification/deployment commands and return the results. Business value: Deterministic policy must surround probabilistic generation. Interview focus: explain where this component sits, how it fails safely and how it is rolled back.
A15: W3-06 | B15: 6 | C15: MUST | D15: Evaluation data | E15: Create 25+ golden cases with sources, facts, tenant and safety tags. | F15: Quality thresholds require versioned, representative truth data. | G15: User | H15: 1.25 | I15: W3-002 | J15: EVAL-001, DATA-001 | K15: Dataset passes schema and privacy review. | L15: python tools/validate_eval_dataset.py configs/eval/golden.jsonl | M15: docs/test-evidence/W3-06-golden.txt | N15: Revert dataset version; never silently edit expected answers. | O15: Not Started | P15: Week 3 owner decision/checkpoint in Evaluation data. You choose, approve or execute “Create 25+ golden cases with sources, facts, tenant and safety tags.” because the decision affects downstream architecture and risk. Codex explains alternatives and may draft approved wording only under the proper approval stage. Business value: Quality thresholds require versioned, representative truth data. Interview focus: explain the decision, trade-off and downstream consequence.
A16: W3-07 | B16: 7 | C16: MUST | D16: Evaluation harness | E16: Measure retrieval, citations, abstention, latency and cost. | F16: Promotion must rely on repeatable evidence, not a demo. | G16: Codex (code) + User (execute) | H16: 1.5 | I16: W3-002 | J16: EVAL-001 | K16: Baseline report and nonzero regression exit behavior exist. | L16: python -m enterprise_ai.evaluation.run --dataset configs/eval/golden.jsonl --out reports/eval.json | M16: reports/eval.json | N16: Restore last approved baseline; block release on unresolved regression. | O16: Not Started | P16: Week 3 Evaluation harness task in the end-to-end architecture. After Code Edit Approval, Codex writes only the approved code/configuration/test code for “Measure retrieval, citations, abstention, latency and cost.”; you run the verification/deployment commands and return the results. Business value: Promotion must rely on repeatable evidence, not a demo. Interview focus: explain where this component sits, how it fails safely and how it is rolled back.
A17: W3-08 | B17: 8 | C17: MUST | D17: Security testing | E17: Test injection, cross-tenant retrieval, unsafe output and logging redaction. | F17: RAG expands the attack surface through untrusted content. | G17: Codex (code) + User (execute) | H17: 1 | I17: W3-003 | J17: SEC-001 | K17: All adversarial fixtures fail safely. | L17: pytest tests/security -q | M17: docs/test-evidence/W3-08-security.txt | N17: Disable affected path; purge/re-index poisoned test document. | O17: Not Started | P17: Week 3 Security testing task in the end-to-end architecture. After Code Edit Approval, Codex writes only the approved code/configuration/test code for “Test injection, cross-tenant retrieval, unsafe output and logging redaction.”; you run the verification/deployment commands and return the results. Business value: RAG expands the attack surface through untrusted content. Interview focus: explain where this component sits, how it fails safely and how it is rolled back.
A18: W3-09 | B18: 9 | C18: MUST | D18: Telemetry | E18: Record retrieval/model/token/guardrail metrics without content. | F18: Stage-level data explains latency, errors and cost. | G18: Codex (code) + User (execute) | H18: 0.75 | I18: W4-003 | J18: OBS-001 | K18: Metrics include versions/outcomes and exclude prompt/document text. | L18: pytest tests/unit/test_telemetry.py -q | M18: docs/test-evidence/W3-09-telemetry.txt | N18: Disable exporter or revert instrumentation, not core answer path. | O18: Not Started | P18: Week 3 Telemetry task in the end-to-end architecture. After Code Edit Approval, Codex writes only the approved code/configuration/test code for “Record retrieval/model/token/guardrail metrics without content.”; you run the verification/deployment commands and return the results. Business value: Stage-level data explains latency, errors and cost. Interview focus: explain where this component sits, how it fails safely and how it is rolled back.
A19: W3-10 | B19: 10 | C19: MUST | D19: Regression gate | E19: Set initial thresholds: Recall@5 >=0.85 and citation-valid/safe-abstain >=95%. | F19: Thresholds convert evaluation into a release decision. | G19: User (execute) + Codex (guide/code) | H19: 0.75 | I19: W3-002 | J19: SLO-001 | K19: CI-style command fails on a material regression. | L19: make evaluate | M19: docs/test-evidence/W3-10-gate.txt | N19: Revert candidate prompt/model/index and preserve failing evidence. | O19: Not Started | P19: Week 3 Regression gate task in the end-to-end architecture. After Code Edit Approval, Codex writes only the approved code/configuration/test code for “Set initial thresholds: Recall@5 >=0.85 and citation-valid/safe-abstain >=95%.”; you run the verification/deployment commands and return the results. Business value: Thresholds convert evaluation into a release decision. Interview focus: explain where this component sits, how it fails safely and how it is rolled back.
A20: W3-11 | B20: 11 | C20: MUST | D20: Rollback drill | E20: Restore prior prompt/model/retriever/index configuration and re-evaluate. | F20: RAG changes can regress without application code changes. | G20: User (execute) + Codex (guide/code) | H20: 1 | I20: W3-ROLLBACK-001 | J20: None | K20: Last-known-good configuration returns baseline results. | L20: make rollback-rag && make evaluate | M20: docs/rollback-records/W3-rag.md | N20: Forward-fix only after a new feature cycle. | O20: Not Started | P20: Week 3 Rollback drill task in the end-to-end architecture. After Code Edit Approval, Codex writes only the approved code/configuration/test code for “Restore prior prompt/model/retriever/index configuration and re-evaluate.”; you run the verification/deployment commands and return the results. Business value: RAG changes can regress without application code changes. Interview focus: explain where this component sits, how it fails safely and how it is rolled back.
A21: W3-12 | B21: 12 | C21: MUST | D21: Checkpoint | E21: Approve cited RAG and quality gate before adding agent behavior. | F21: Agent tools should not be added to an ungrounded answer system. | G21: User | H21: 0.75 | I21: W3-REVIEW-001 | J21: APP-001 | K21: Grounded answer or abstention works; security/regression/rollback tests pass. | L21: make test && make evaluate | M21: docs/deployment-records/W3-signoff.md | N21: Keep agent endpoints disabled until approved. | O21: Not Started | P21: Week 3 business/decision documentation task in Checkpoint. The owner provides or approves the facts; after Document Writing Approval, Codex may draft only the approved business-first documentation. No code or command execution is permitted. Business value: Agent tools should not be added to an ungrounded answer system. Interview focus: explain the decision, its alternatives and downstream impact.
A22: W3-13 | B22: 13 | C22: MUST | D22: Weekly learning | E22: Complete the Week 3 cited-RAG business, architecture and interview teach-back. | F22: Builds confidence explaining grounded answers, abstention, evaluation and model-provider boundaries. | G22: User (execute) + Codex (guide/code) | H22: 1 | I22: WEEKLY-LEARN-001 | J22: None | K22: Owner explains cited RAG, guardrails, evaluation thresholds, rollback and three interview answers. | L22: Owner teach-back; no command | M22: docs/learning/W3-learning-review.md | N22: No runtime rollback; revise the learning note through document approval if inaccurate. | O22: Not Started | P22: Week 3 learning gate after all implementation and checkpoint work. Codex teaches the business outcome and architecture; the owner completes a teach-back and interview practice. No runtime action is permitted. Business value: converts completed work into reusable understanding and decision ownership.
A24: Grouped prompt sequence — full Main / Code Edit / Document Writing / Final Approval prompts are in 10 Codex Prompts
A25: Order | B25: Prompt ID | C25: Feature | D25: Purpose | E25: Required Inputs | F25: Expected Outputs | G25: Example Usage
A26: 1 | B26: W3-001 | C26: LLM adapters and cited RAG pipeline | D26: Generate evidence-bound answers while retaining provider portability. | E26: LLM_PROVIDER, LLM_MODEL_ID, AWS_REGION; Bedrock test is marked | F26: LLM protocol, fake/Bedrock adapters, prompt loader, RAG service and tests | G26: Review Main Prompt → Column L code approval → owner runs TEST-001 guidance → Column M documents → Column N final approval
A27: 2 | B27: W3-002 | C27: Evaluation harness and release gate | D27: Replace subjective demonstrations with repeatable evidence. | E27: configs/eval/golden.jsonl with 25+ approved cases | F27: JSONL schema, deterministic metrics, Ragas adapter, baseline and report | G27: Review Main Prompt → Column L code approval → owner runs TEST-001 guidance → Column M documents → Column N final approval
A28: 3 | B28: W3-003 | C28: RAG guardrails and security regression suite | D28: Treat retrieved content as untrusted and enforce authorization outside the model. | E28: Classification/tenant rules; injection fixtures | F28: Input/output validators, citation/abstention gates, security tests | G28: Review Main Prompt → Column L code approval → owner runs TEST-001 guidance → Column M documents → Column N final approval
A29: 4 | B29: W3-ROLLBACK-001 | C29: Cited-RAG configuration rollback drill | D29: Prove prompt/model/retriever/index configuration can return to a known-good baseline. | E29: Approved baseline and exact local configuration paths from the pre-edit plan | F29: Restored configuration and docs/rollback-records/W3-rag.md | G29: Review Main Prompt → Column L code approval → owner runs TEST-001 guidance → Column M documents → Column N final approval
A30: 5 | B30: W3-REVIEW-001 | C30: Reusable weekly checkpoint | D30: Stop between weeks until MUST work, evidence, decisions, TODOs and rollback readiness are reviewed. | E30: Week 3 sheet, evidence register, ADRs, TODOs and owner-supplied results | F30: docs/deployment-records/W3-signoff.md | G30: Review Main Prompt → Column M document approval → owner review → Column N final approval
A31: 6 | B31: WEEKLY-LEARN-001 | C31: Week 3 owner learning and interview teach-back | D31: Teach the completed week's business outcome, architecture, decisions, trade-offs and failure/rollback story. | E31: Completed weekly tasks, owner-executed results, approved decisions and documentation | F31: Owner teach-back and optional docs/learning/W3-learning-review.md | G31: Use after all weekly work and final approvals; no code or runtime action

Sheet 06 W4 API and Agent
A1: Week 4 — API and Agent
A2: Controlled API and agent: FastAPI, LangGraph, budgets, human approval, redacted state, telemetry and release rollback.
A4: Progress | D4: Blocked | G4: Exit gate
A5: =IF(COUNTA(O10:O40)=0,0,COUNTIF(O10:O40,"Done")/COUNTA(A10:A40)) -> 0 | D5: =COUNTIF(O10:O40,"Blocked") -> 0 | G5: Write action cannot execute without policy and durable approval; previous release restores successfully.
A9: Step ID | B9: Seq | C9: Priority | D9: Workstream | E9: Action | F9: Architecture Reason | G9: Owner | H9: Effort | I9: Prompt | J9: User TODO | K9: Acceptance | L9: Owner Verify | M9: Evidence | N9: Rollback/Teardown | O9: Status | P9: Task Context
A10: W4-01 | B10: 1 | C10: MUST | D10: API | E10: Implement health, query and agent endpoints using dependency interfaces. | F10: A thin typed boundary isolates clients from implementation details. | G10: Codex (code) + User (execute) | H10: 1.5 | I10: W4-001 | J10: SEC-001 | K10: Endpoints return normalized schemas and request IDs. | L10: pytest tests/unit/test_api.py -q | M10: docs/test-evidence/W4-01-api.txt | N10: Roll back image/config and disable new route. | O10: Not Started | P10: Week 4 API task in the end-to-end architecture. After Code Edit Approval, Codex writes only the approved code/configuration/test code for “Implement health, query and agent endpoints using dependency interfaces.”; you run the verification/deployment commands and return the results. Business value: A thin typed boundary isolates clients from implementation details. Interview focus: explain where this component sits, how it fails safely and how it is rolled back.
A11: W4-02 | B11: 2 | C11: MUST | D11: Authorization | E11: Implement auth context interface and deny before retrieval/action. | F11: Identity and authorization are deterministic platform controls. | G11: Codex (code) + User (execute) | H11: 1 | I11: W4-001 | J11: SEC-001 | K11: Unauthorized query never invokes retriever or tool. | L11: pytest tests/security/test_api_authorization.py -q | M11: docs/test-evidence/W4-02-auth.txt | N11: Disable endpoint or restore previous auth dependency. | O11: Not Started | P11: Week 4 Authorization task in the end-to-end architecture. After Code Edit Approval, Codex writes only the approved code/configuration/test code for “Implement auth context interface and deny before retrieval/action.”; you run the verification/deployment commands and return the results. Business value: Identity and authorization are deterministic platform controls. Interview focus: explain where this component sits, how it fails safely and how it is rolled back.
A12: W4-03 | B12: 3 | C12: MUST | D12: Agent state | E12: Define typed LangGraph state, explicit nodes and terminal outcomes. | F12: Agents are bounded workflows, not autonomous black boxes. | G12: Codex (code) + User (execute) | H12: 1.25 | I12: W4-002 | J12: APP-001 | K12: Every path reaches answer, denied, rejected, timed-out or safe-terminal. | L12: pytest tests/unit/test_agent_graph.py -q | M12: docs/test-evidence/W4-03-graph.txt | N12: Feature flag disables graph; query endpoint remains read-only. | O12: Not Started | P12: Week 4 Agent state task in the end-to-end architecture. After Code Edit Approval, Codex writes only the approved code/configuration/test code for “Define typed LangGraph state, explicit nodes and terminal outcomes.”; you run the verification/deployment commands and return the results. Business value: Agents are bounded workflows, not autonomous black boxes. Interview focus: explain where this component sits, how it fails safely and how it is rolled back.
A13: W4-04 | B13: 4 | C13: MUST | D13: Tools | E13: Add one read-only status tool with narrow schema. | F13: Read-only tool proves integration at low consequence. | G13: Codex (code) + User (execute) | H13: 0.75 | I13: W4-002 | J13: None | K13: Allowlist and JSON schema reject malformed calls. | L13: pytest tests/unit/test_agent_tools.py -q | M13: docs/test-evidence/W4-04-read-tool.txt | N13: Remove tool registration and restore prior graph. | O13: Not Started | P13: Week 4 Tools task in the end-to-end architecture. After Code Edit Approval, Codex writes only the approved code/configuration/test code for “Add one read-only status tool with narrow schema.”; you run the verification/deployment commands and return the results. Business value: Read-only tool proves integration at low consequence. Interview focus: explain where this component sits, how it fails safely and how it is rolled back.
A14: W4-05 | B14: 5 | C14: MUST | D14: Human approval | E14: Add mocked write tool that requires durable approval. | F14: Consequential actions cannot rely on model intent. | G14: Codex (code) + User (execute) | H14: 1.25 | I14: W4-002 | J14: APP-001 | K14: No approval/rejection/expired approval prevents execution. | L14: pytest tests/security/test_agent_approval.py -q | M14: docs/test-evidence/W4-05-approval.txt | N14: Disable write-tool feature flag and invalidate pending approvals. | O14: Not Started | P14: Week 4 Human approval task in the end-to-end architecture. After Code Edit Approval, Codex writes only the approved code/configuration/test code for “Add mocked write tool that requires durable approval.”; you run the verification/deployment commands and return the results. Business value: Consequential actions cannot rely on model intent. Interview focus: explain where this component sits, how it fails safely and how it is rolled back.
A15: W4-06 | B15: 6 | C15: MUST | D15: Budgets | E15: Enforce step, tool-call, token/time deadline and retry limits. | F15: Bounds prevent loops, retry storms and unplanned model spend. | G15: Codex (code) + User (execute) | H15: 1 | I15: W4-002 | J15: COST-001 | K15: Budget-exceeded paths stop safely and record reason. | L15: pytest tests/unit/test_agent_budgets.py -q | M15: docs/test-evidence/W4-06-budgets.txt | N15: Reduce limits or disable agent route. | O15: Not Started | P15: Week 4 Budgets task in the end-to-end architecture. After Code Edit Approval, Codex writes only the approved code/configuration/test code for “Enforce step, tool-call, token/time deadline and retry limits.”; you run the verification/deployment commands and return the results. Business value: Bounds prevent loops, retry storms and unplanned model spend. Interview focus: explain where this component sits, how it fails safely and how it is rolled back.
A16: W4-07 | B16: 7 | C16: MUST | D16: State security | E16: Persist only redacted agent state and audit decisions. | F16: Checkpoints must not become a secret/PII store. | G16: Codex (code) + User (execute) | H16: 0.75 | I16: W4-002 | J16: RET-001 | K16: State fixture contains IDs/outcomes but no content/secrets. | L16: pytest tests/security/test_agent_state_redaction.py -q | M16: docs/test-evidence/W4-07-state.txt | N16: Purge test checkpoints and restore safe serializer. | O16: Not Started | P16: Week 4 State security task in the end-to-end architecture. After Code Edit Approval, Codex writes only the approved code/configuration/test code for “Persist only redacted agent state and audit decisions.”; you run the verification/deployment commands and return the results. Business value: Checkpoints must not become a secret/PII store. Interview focus: explain where this component sits, how it fails safely and how it is rolled back.
A17: W4-08 | B17: 8 | C17: MUST | D17: Observability | E17: Trace API to retrieval, LLM, guardrail, approval and tool. | F17: Correlated traces make probabilistic workflows diagnosable. | G17: Codex (code) + User (execute) | H17: 1 | I17: W4-003 | J17: OBS-001 | K17: One local trace contains all stages and safe attributes. | L17: pytest tests/feature/test_trace_correlation.py -q | M17: docs/test-evidence/W4-08-trace.json | N17: Disable exporter; preserve local logs and core service. | O17: Not Started | P17: Week 4 Observability task in the end-to-end architecture. After Code Edit Approval, Codex writes only the approved code/configuration/test code for “Trace API to retrieval, LLM, guardrail, approval and tool.”; you run the verification/deployment commands and return the results. Business value: Correlated traces make probabilistic workflows diagnosable. Interview focus: explain where this component sits, how it fails safely and how it is rolled back.
A18: W4-09 | B18: 9 | C18: MUST | D18: Failure testing | E18: Exercise denial, malformed args, injection, timeout, loop and rejection. | F18: Agent safety is proven through negative paths. | G18: Codex (code) + User (execute) | H18: 1 | I18: W4-002 | J18: None | K18: All failure modes terminate without write side effects. | L18: pytest tests/security/test_agent_* tests/feature/test_agent_failures.py -q | M18: docs/test-evidence/W4-09-failures.txt | N18: Disable agent endpoint and preserve evidence. | O18: Not Started | P18: Week 4 Failure testing task in the end-to-end architecture. After Code Edit Approval, Codex writes only the approved code/configuration/test code for “Exercise denial, malformed args, injection, timeout, loop and rejection.”; you run the verification/deployment commands and return the results. Business value: Agent safety is proven through negative paths. Interview focus: explain where this component sits, how it fails safely and how it is rolled back.
A19: W4-10 | B19: 10 | C19: SHOULD | D19: Performance | E19: Run bounded local smoke/load test with fake/approved model. | F19: Concurrency and timeouts must fail predictably before EKS. | G19: Codex (code) + User (execute) | H19: 0.75 | I19: W4-001 | J19: COST-001 | K19: No unbounded queue; p95/p99 baseline is recorded. | L19: pytest tests/feature/test_api_load_smoke.py -q | M19: docs/test-evidence/W4-10-load.json | N19: Reduce traffic; revert concurrency settings. | O19: Not Started | P19: Week 4 Performance task in the end-to-end architecture. After Code Edit Approval, Codex writes only the approved code/configuration/test code for “Run bounded local smoke/load test with fake/approved model.”; you run the verification/deployment commands and return the results. Business value: Concurrency and timeouts must fail predictably before EKS. Interview focus: explain where this component sits, how it fails safely and how it is rolled back.
A20: W4-11 | B20: 11 | C20: MUST | D20: Release rollback | E20: Deploy local immutable version N+1, force regression and restore N. | F20: Release rollback is separate from infrastructure rollback. | G20: User (execute) + Codex (guide/code) | H20: 1 | I20: W4-ROLLBACK-001 | J20: None | K20: N becomes healthy and passes feature tests after rollback. | L20: make rollback-release && make smoke | M20: docs/rollback-records/W4-release.md | N20: Keep agent route disabled until the failure is fixed. | O20: Not Started | P20: Week 4 Release rollback task in the end-to-end architecture. After Code Edit Approval, Codex writes only the approved code/configuration/test code for “Deploy local immutable version N+1, force regression and restore N.”; you run the verification/deployment commands and return the results. Business value: Release rollback is separate from infrastructure rollback. Interview focus: explain where this component sits, how it fails safely and how it is rolled back.
A21: W4-12 | B21: 12 | C21: MUST | D21: Checkpoint | E21: Approve controlled API/agent and Week 5 AWS inputs. | F21: Cloud infrastructure should not be planned for an unsafe runtime. | G21: User | H21: 0.75 | I21: W4-REVIEW-001 | J21: AWS-001, AWS-002, NET-001, TAG-001, COST-001 | K21: All consequential actions are policy-valid and approved. | L21: make test && make security-scan | M21: docs/deployment-records/W4-signoff.md | N21: Do not begin Terraform plan until inputs and cost ceiling are approved. | O21: Not Started | P21: Week 4 business/decision documentation task in Checkpoint. The owner provides or approves the facts; after Document Writing Approval, Codex may draft only the approved business-first documentation. No code or command execution is permitted. Business value: Cloud infrastructure should not be planned for an unsafe runtime. Interview focus: explain the decision, its alternatives and downstream impact.
A22: W4-13 | B22: 13 | C22: MUST | D22: Weekly learning | E22: Complete the Week 4 API/agent business, architecture and interview teach-back. | F22: Makes bounded agents, human approval, API controls and observability explainable to business and technical interviewers. | G22: User (execute) + Codex (guide/code) | H22: 1 | I22: WEEKLY-LEARN-001 | J22: None | K22: Owner explains API boundaries, authorization, agent state/budgets, human approval, telemetry and three interview answers. | L22: Owner teach-back; no command | M22: docs/learning/W4-learning-review.md | N22: No runtime rollback; revise the learning note through document approval if inaccurate. | O22: Not Started | P22: Week 4 learning gate after all implementation and checkpoint work. Codex teaches the business outcome and architecture; the owner completes a teach-back and interview practice. No runtime action is permitted. Business value: converts completed work into reusable understanding and decision ownership.
A24: Grouped prompt sequence — full Main / Code Edit / Document Writing / Final Approval prompts are in 10 Codex Prompts
A25: Order | B25: Prompt ID | C25: Feature | D25: Purpose | E25: Required Inputs | F25: Expected Outputs | G25: Example Usage
A26: 1 | B26: W4-001 | C26: FastAPI service boundary | D26: Expose production-shaped, testable endpoints. | E26: Fake providers by default; auth interface choice | F26: FastAPI endpoints, schemas, dependencies, health, error mapping and tests | G26: Review Main Prompt → Column L code approval → owner runs TEST-001 guidance → Column M documents → Column N final approval
A27: 2 | B27: W4-002 | C27: Bounded LangGraph agent controller | D27: Add controlled agent behavior without uncontrolled autonomy. | E27: Step/tool/time budgets; approval-store decision | F27: Typed graph, nodes/edges, approval interrupt, tools, tests and Mermaid | G27: Review Main Prompt → Column L code approval → owner runs TEST-001 guidance → Column M documents → Column N final approval
A28: 3 | B28: W4-003 | C28: Application telemetry and redacted audit trail | D28: Make each RAG and agent stage explainable operationally. | E28: OTEL exporter endpoint; no content export | F28: Telemetry module, structured logs, trace tests and local collector config | G28: Review Main Prompt → Column L code approval → owner runs TEST-001 guidance → Column M documents → Column N final approval
A29: 4 | B29: W4-ROLLBACK-001 | C29: Local immutable release rollback drill | D29: Prove release rollback separately from infrastructure rollback. | E29: Approved local immutable releases N and N+1 and safe regression method | F29: Restored release N and docs/rollback-records/W4-release.md | G29: Review Main Prompt → Column L code approval → owner runs TEST-001 guidance → Column M documents → Column N final approval
A30: 5 | B30: W4-REVIEW-001 | C30: Reusable weekly checkpoint | D30: Stop between weeks until MUST work, evidence, decisions, TODOs and rollback readiness are reviewed. | E30: Week 4 sheet, evidence register, ADRs, TODOs and owner-supplied results | F30: docs/deployment-records/W4-signoff.md | G30: Review Main Prompt → Column M document approval → owner review → Column N final approval
A31: 6 | B31: WEEKLY-LEARN-001 | C31: Week 4 owner learning and interview teach-back | D31: Teach the completed week's business outcome, architecture, decisions, trade-offs and failure/rollback story. | E31: Completed weekly tasks, owner-executed results, approved decisions and documentation | F31: Owner teach-back and optional docs/learning/W4-learning-review.md | G31: Use after all weekly work and final approvals; no code or runtime action

Sheet 07 W5 AWS Lifecycle
A1: Week 5 — AWS Lifecycle
A2: AWS lifecycle proof: Terraform/policy/CI, reviewed plans, short-lived identity, deploy/rollback/teardown capability and orphan scan.
A4: Progress | D4: Blocked | G4: Exit gate
A5: =IF(COUNTA(O10:O40)=0,0,COUNTIF(O10:O40,"Done")/COUNTA(A10:A40)) -> 0 | D5: =COUNTIF(O10:O40,"Blocked") -> 0 | G5: Terraform/policy/plan/lifecycle evidence passes; no plaintext secret or unexpected unmanaged resource.
A9: Step ID | B9: Seq | C9: Priority | D9: Workstream | E9: Action | F9: Architecture Reason | G9: Owner | H9: Effort | I9: Prompt | J9: User TODO | K9: Acceptance | L9: Owner Verify | M9: Evidence | N9: Rollback/Teardown | O9: Status | P9: Task Context
A10: W5-01 | B10: 1 | C10: MUST | D10: AWS inputs | E10: Confirm sandbox account, region, network, tags, data residency and budget ceiling. | F10: Terraform cannot be safely reviewed with ambiguous ownership or cost. | G10: User | H10: 1 | I10: W5-INPUTS-001 | J10: AWS-001, AWS-002, NET-001, TAG-001, COST-001, PRIV-001 | K10: All variables are non-secret and approved. | L10: Review infra/environments/sandbox/terraform.tfvars.example | M10: docs/cost-estimates/W5-inputs.md | N10: Do not initialize/apply until inputs are approved. | O10: Not Started | P10: Week 5 business/decision documentation task in AWS inputs. The owner provides or approves the facts; after Document Writing Approval, Codex may draft only the approved business-first documentation. No code or command execution is permitted. Business value: Terraform cannot be safely reviewed with ambiguous ownership or cost. Interview focus: explain the decision, its alternatives and downstream impact.
A11: W5-02 | B11: 2 | C11: MUST | D11: State bootstrap | E11: Build isolated encrypted/versioned S3 state and Terraform 1.5 DynamoDB locking stack. | F11: State must survive platform rollback and be removed last during full teardown. | G11: Codex (code) + User (execute) | H11: 1.25 | I11: W5-001 | J11: AWS-001, AWS-002, TAG-001 | K11: fmt/validate/Checkov pass; apply remains manual. | L11: terraform -chdir=infra/bootstrap fmt -check && terraform -chdir=infra/bootstrap validate | M11: docs/test-evidence/W5-02-bootstrap.txt | N11: Destroy platform first; bootstrap destroy is separately reviewed. | O11: Not Started | P11: Week 5 State bootstrap task in the end-to-end architecture. After Code Edit Approval, Codex writes only the approved code/configuration/test code for “Build isolated encrypted/versioned S3 state and Terraform 1.5 DynamoDB locking stack.”; you run the verification/deployment commands and return the results. Business value: State must survive platform rollback and be removed last during full teardown. Interview focus: explain where this component sits, how it fails safely and how it is rolled back.
A12: W5-03 | B12: 3 | C12: MUST | D12: Security foundation | E12: Create KMS, private/versioned S3 and secret-metadata modules. | F12: Encryption and secret separation are foundational controls. | G12: Codex (code) + User (execute) | H12: 1.25 | I12: W5-001 | J12: KMS-001, TAG-001 | K12: No public access or secret value resource exists. | L12: terraform -chdir=infra/environments/sandbox validate && checkov -d infra/modules | M12: docs/test-evidence/W5-03-security.txt | N12: Apply prior Terraform version; use purge only for disposable sandbox. | O12: Not Started | P12: Week 5 Security foundation task in the end-to-end architecture. After Code Edit Approval, Codex writes only the approved code/configuration/test code for “Create KMS, private/versioned S3 and secret-metadata modules.”; you run the verification/deployment commands and return the results. Business value: Encryption and secret separation are foundational controls. Interview focus: explain where this component sits, how it fails safely and how it is rolled back.
A13: W5-04 | B13: 4 | C13: MUST | D13: IAM | E13: Create least-privilege runtime, ingestion and GitHub OIDC roles. | F13: Workloads need short-lived, separated permissions. | G13: Codex (code) + User (execute) | H13: 1.25 | I13: W5-001 | J13: GHA-001, BED-001, TAG-001 | K13: No wildcard action/resource without reviewed exception. | L13: checkov -d infra && opa test policies/opa -v | M13: docs/test-evidence/W5-04-iam.txt | N13: Disable role session/restore prior policy; do not store keys. | O13: Not Started | P13: Week 5 IAM task in the end-to-end architecture. After Code Edit Approval, Codex writes only the approved code/configuration/test code for “Create least-privilege runtime, ingestion and GitHub OIDC roles.”; you run the verification/deployment commands and return the results. Business value: Workloads need short-lived, separated permissions. Interview focus: explain where this component sits, how it fails safely and how it is rolled back.
A14: W5-05 | B14: 5 | C14: MUST | D14: AWS retrieval | E14: Create private encrypted OpenSearch and ECR modules. | F14: OpenSearch is the AWS vector target; ECR stores immutable images. | G14: Codex (code) + User (execute) | H14: 1.5 | I14: W5-001 | J14: NET-001, TAG-001 | K14: Private network, TLS, encryption, logs and access controls are planned. | L14: terraform -chdir=infra/environments/sandbox plan -out=tfplan | M14: docs/test-evidence/W5-05-platform-plan.txt | N14: Apply reviewed previous Terraform version or destroy disposable resources in order. | O14: Not Started | P14: Week 5 AWS retrieval task in the end-to-end architecture. After Code Edit Approval, Codex writes only the approved code/configuration/test code for “Create private encrypted OpenSearch and ECR modules.”; you run the verification/deployment commands and return the results. Business value: OpenSearch is the AWS vector target; ECR stores immutable images. Interview focus: explain where this component sits, how it fails safely and how it is rolled back.
A15: W5-06 | B15: 6 | C15: MUST | D15: Policy as code | E15: Implement OPA and Checkov security/tagging policies with fixtures. | F15: Policy gates make critical architecture decisions executable. | G15: Codex (code) + User (execute) | H15: 1 | I15: W5-003 | J15: AWS-002, TAG-001 | K15: Insecure fixtures fail; secure fixtures pass. | L15: opa test policies/opa -v && checkov -d infra | M15: docs/test-evidence/W5-06-policy.txt | N15: Revert candidate policy only through reviewed exception/ADR. | O15: Not Started | P15: Week 5 Policy as code task in the end-to-end architecture. After Code Edit Approval, Codex writes only the approved code/configuration/test code for “Implement OPA and Checkov security/tagging policies with fixtures.”; you run the verification/deployment commands and return the results. Business value: Policy gates make critical architecture decisions executable. Interview focus: explain where this component sits, how it fails safely and how it is rolled back.
A16: W5-07 | B16: 7 | C16: MUST | D16: CI/CD | E16: Create PR CI and Terraform-plan workflow using GitHub OIDC. | F16: Automated gates and short-lived identity reduce change and credential risk. | G16: Codex (code) + User (execute) | H16: 1.5 | I16: W5-002 | J16: GHA-001 | K16: All required checks run; apply/destroy are owner-gated. | L16: Review .github/workflows and run actionlint if available | M16: docs/test-evidence/W5-07-ci.txt | N16: Disable workflow; revoke OIDC trust; keep last good release. | O16: Not Started | P16: Week 5 CI/CD task in the end-to-end architecture. After Code Edit Approval, Codex writes only the approved code/configuration/test code for “Create PR CI and Terraform-plan workflow using GitHub OIDC.”; you run the verification/deployment commands and return the results. Business value: Automated gates and short-lived identity reduce change and credential risk. Interview focus: explain where this component sits, how it fails safely and how it is rolled back.
A17: W5-08 | B17: 8 | C17: MUST | D17: Supply chain | E17: Build image, scan with Trivy/Grype and generate Syft SBOM. | F17: Deployment must use a known, scanned immutable artifact. | G17: Codex (code) + User (execute) | H17: 1 | I17: W5-002 | J17: None | K17: Critical findings fail per policy and SBOM is retained. | L17: docker build -t enterprise-ai:test . && trivy image enterprise-ai:test | M17: docs/test-evidence/W5-08-supply-chain.txt | N17: Do not publish vulnerable digest; restore prior approved digest. | O17: Not Started | P17: Week 5 Supply chain task in the end-to-end architecture. After Code Edit Approval, Codex writes only the approved code/configuration/test code for “Build image, scan with Trivy/Grype and generate Syft SBOM.”; you run the verification/deployment commands and return the results. Business value: Deployment must use a known, scanned immutable artifact. Interview focus: explain where this component sits, how it fails safely and how it is rolled back.
A18: W5-09 | B18: 9 | C18: MUST | D18: Plan review | E18: Generate saved Terraform plan, JSON policy result and human-readable summary. | F18: Applying the reviewed bytes prevents unseen infrastructure change. | G18: User (execute) + Codex (guide/code) | H18: 1 | I18: W5-004 | J18: COST-001 | K18: Plan, policy and cost review are approved before any apply. | L18: make plan-sandbox | M18: docs/deployment-records/W5-plan-review.md | N18: Discard saved plan on code/input drift and regenerate. | O18: Not Started | P18: Week 5 Plan review task in the end-to-end architecture. After Code Edit Approval, Codex writes only the approved code/configuration/test code for “Generate saved Terraform plan, JSON policy result and human-readable summary.”; you run the verification/deployment commands and return the results. Business value: Applying the reviewed bytes prevents unseen infrastructure change. Interview focus: explain where this component sits, how it fails safely and how it is rolled back.
A19: W5-10 | B19: 10 | C19: MUST | D19: Sandbox lifecycle | E19: After explicit approval, deploy/validate/rollback/destroy in controlled sequence. | F19: Capability must be proven, but Codex must never self-approve mutations. | G19: User | H19: 1.5 | I19: W5-004 | J19: DEST-001 | K19: Reviewed plan applies; validation passes; rollback path is recorded. | L19: make deploy-sandbox # owner-approved only | M19: docs/deployment-records/W5-sandbox.md | N19: Use last-known-good Terraform version; destroy is not ordinary rollback. | O19: Not Started | P19: Week 5 owner decision/checkpoint in Sandbox lifecycle. You choose, approve or execute “After explicit approval, deploy/validate/rollback/destroy in controlled sequence.” because the decision affects downstream architecture and risk. Codex explains alternatives and may draft approved wording only under the proper approval stage. Business value: Capability must be proven, but Codex must never self-approve mutations. Interview focus: explain the decision, trade-off and downstream consequence.
A20: W5-11 | B20: 11 | C20: MUST | D20: Teardown plan | E20: Create and review platform destroy plan; preserve bootstrap until platform is gone. | F20: Deletion order prevents dependency residue and loss of auditability. | G20: User (execute) + Codex (guide/code) | H20: 0.75 | I20: W5-004 | J20: DEST-001 | K20: Destroy plan targets only approved sandbox resources. | L20: make plan-destroy-sandbox | M20: docs/deployment-records/W5-destroy-plan.md | N20: Cancel before apply if any unexpected target appears. | O20: Not Started | P20: Week 5 Teardown plan task in the end-to-end architecture. After Code Edit Approval, Codex writes only the approved code/configuration/test code for “Create and review platform destroy plan; preserve bootstrap until platform is gone.”; you run the verification/deployment commands and return the results. Business value: Deletion order prevents dependency residue and loss of auditability. Interview focus: explain where this component sits, how it fails safely and how it is rolled back.
A21: W5-12 | B21: 12 | C21: MUST | D21: Cleanliness proof | E21: Run verify-clean using required tags and native service APIs after approved teardown. | F21: A successful Terraform destroy is not proof of zero residual resources. | G21: User (execute) + Codex (guide/code) | H21: 1 | I21: W5-004 | J21: TAG-001, KMS-001 | K21: No active unmanaged resource remains; exception is documented PendingDeletion KMS key. | L21: make destroy-sandbox && make verify-clean # owner-approved only | M21: docs/resource-cleanliness/W5-report.json | N21: Remove residuals in dependency order; do not delete bootstrap until clean. | O21: Not Started | P21: Week 5 Cleanliness proof task in the end-to-end architecture. After Code Edit Approval, Codex writes only the approved code/configuration/test code for “Run verify-clean using required tags and native service APIs after approved teardown.”; you run the verification/deployment commands and return the results. Business value: A successful Terraform destroy is not proof of zero residual resources. Interview focus: explain where this component sits, how it fails safely and how it is rolled back.
... A23: W5-14 | B23: 14 | C23: MUST | D23: Weekly learning | E23: Complete the Week 5 AWS lifecycle business, architecture and interview teach-back. | F23: Connects infrastructure-as-code, identity, policy, supply chain, cost and teardown into a controlled cloud story. | G23: User (execute) + Codex (guide/code) | H23: 1 | I23: WEEKLY-LEARN-001 | J23: None | K23: Owner explains reviewed plans, OIDC, policy gates, immutable artifacts, rollback/teardown and three interview answers. | L23: Owner teach-back; no command | M23: docs/learning/W5-learning-review.md | N23: No runtime rollback; revise the learning note through document approval if inaccurate. | O23: Not Started | P23: Week 5 learning gate after all implementation and checkpoint work. Codex teaches the business outcome and architecture; the owner completes a teach-back and interview practice. No runtime action is permitted. Business value: converts completed work into reusable understanding and decision ownership.
A25: Grouped prompt sequence — full Main / Code Edit / Document Writing / Final Approval prompts are in 10 Codex Prompts
A26: Order | B26: Prompt ID | C26: Feature | D26: Purpose | E26: Required Inputs | F26: Expected Outputs | G26: Example Usage
A27: 1 | B27: W5-INPUTS-001 | C27: AWS sandbox input approval | D27: Capture all non-secret AWS, network, tagging, residency and budget choices before Terraform work. | E27: AWS-001, AWS-002, NET-001, TAG-001, COST-001 and PRIV-001; no credentials | F27: Non-secret tfvars example and docs/cost-estimates/W5-inputs.md | G27: Review Main Prompt → Column M document approval → owner review → Column N final approval
A28: 2 | B28: W5-001 | C28: Terraform AWS sandbox modules | D28: Produce reviewable infrastructure without secret material. | E28: TODO account, region, VPC/subnets, GitHub repo, tags, Bedrock models | F28: Bootstrap and KMS/S3/IAM/OpenSearch/ECR/secret-metadata modules | G28: Review Main Prompt → Column L code approval → owner runs TEST-001 guidance → Column M documents → Column N final approval
A29: 3 | B29: W5-002 | C29: GitHub Actions DevSecOps pipeline | D29: Enforce quality, IaC and supply-chain gates with short-lived identity. | E29: GitHub environment, OIDC role ARN, sandbox variables | F29: PR CI, Terraform plan workflow, image/SBOM scans and approval-gated deploy shell | G29: Review Main Prompt → Column L code approval → owner runs TEST-001 guidance → Column M documents → Column N final approval
A30: 4 | B30: W5-003 | C30: OPA and Checkov policy pack | D30: Make critical cloud controls executable before apply. | E30: Approved regions, encryption/tag rules, exception process | F30: Rego policies/tests, Checkov custom policies and fixtures | G30: Review Main Prompt → Column L code approval → owner runs TEST-001 guidance → Column M documents → Column N final approval
A31: 5 | B31: W5-004 | C31: Reviewed deploy, rollback, teardown and orphan scan | D31: Prove the AWS lifecycle without leaving unmanaged resources. | E31: Approved saved plan; budget ceiling; typed owner confirmations | F31: platformctl AWS implementations, deployment/rollback/destroy records, cleanup report | G31: Review Main Prompt → Column L code approval → owner runs TEST-001 guidance → Column M documents → Column N final approval
A32: 6 | B32: W5-REVIEW-001 | C32: Reusable weekly checkpoint | D32: Stop between weeks until MUST work, evidence, decisions, TODOs and rollback readiness are reviewed. | E32: Week 5 sheet, evidence register, ADRs, TODOs and owner-supplied results | F32: docs/deployment-records/W5-signoff.md | G32: Review Main Prompt → Column M document approval → owner review → Column N final approval
A33: 7 | B33: WEEKLY-LEARN-001 | C33: Week 5 owner learning and interview teach-back | D33: Teach the completed week's business outcome, architecture, decisions, trade-offs and failure/rollback story. | E33: Completed weekly tasks, owner-executed results, approved decisions and documentation | F33: Owner teach-back and optional docs/learning/W5-learning-review.md | G33: Use after all weekly work and final approvals; no code or runtime action

Sheet 08 W6 EKS and SRE
A1: Week 6 — EKS and SRE
A2: EKS/SRE final proof: immutable workload, identity/network/resilience, SLOs/runbook/chaos, rollback and complete teardown.
A4: Progress | D4: Blocked | G4: Exit gate
A5: =IF(COUNTA(O10:O40)=0,0,COUNTIF(O10:O40,"Done")/COUNTA(A10:A40)) -> 0 | D5: =COUNTIF(O10:O40,"Blocked") -> 0 | G5: End-to-end RAG meets gates; release rollback and full teardown/cleanliness proof are signed.
A9: Step ID | B9: Seq | C9: Priority | D9: Workstream | E9: Action | F9: Architecture Reason | G9: Owner | H9: Effort | I9: Prompt | J9: User TODO | K9: Acceptance | L9: Owner Verify | M9: Evidence | N9: Rollback/Teardown | O9: Status | P9: Task Context
A10: W6-01 | B10: 1 | C10: MUST | D10: Artifact promotion | E10: Publish scanned image to ECR by immutable digest. | F10: Rollback and provenance require immutable deployment identity. | G10: User (execute) + Codex (guide/code) | H10: 0.75 | I10: W5-002 | J10: EKS-001 | K10: Digest matches the scanned/SBOM artifact. | L10: docker inspect --format='{{index .RepoDigests 0}}' enterprise-ai:test | M10: docs/deployment-records/W6-image.md | N10: Restore prior approved digest; never reuse a mutable tag as authority. | O10: Not Started | P10: Week 6 Artifact promotion task in the end-to-end architecture. After Code Edit Approval, Codex writes only the approved code/configuration/test code for “Publish scanned image to ECR by immutable digest.”; you run the verification/deployment commands and return the results. Business value: Rollback and provenance require immutable deployment identity. Interview focus: explain where this component sits, how it fails safely and how it is rolled back.
A11: W6-02 | B11: 2 | C11: MUST | D11: Kubernetes | E11: Create EKS deployment/Service with non-root/read-only settings and probes. | F11: Production-shaped runtime boundaries reduce container and availability risk. | G11: Codex (code) + User (execute) | H11: 1.5 | I11: W6-001 | J11: EKS-001 | K11: Server dry-run and policy validation pass. | L11: kubectl apply --dry-run=server -f deploy/k8s | M11: docs/test-evidence/W6-02-k8s.txt | N11: kubectl rollout undo or redeploy previous digest. | O11: Not Started | P11: Week 6 Kubernetes task in the end-to-end architecture. After Code Edit Approval, Codex writes only the approved code/configuration/test code for “Create EKS deployment/Service with non-root/read-only settings and probes.”; you run the verification/deployment commands and return the results. Business value: Production-shaped runtime boundaries reduce container and availability risk. Interview focus: explain where this component sits, how it fails safely and how it is rolled back.
A12: W6-03 | B12: 3 | C12: MUST | D12: Workload identity | E12: Configure EKS Pod Identity/IRSA, RBAC and least-privilege service account. | F12: Pods must never contain static AWS credentials. | G12: Codex (code) + User (execute) | H12: 1 | I12: W6-001 | J12: AWS-001, EKS-001 | K12: Pod accesses only required AWS APIs and env has no static key. | L12: kubectl exec deploy/enterprise-ai-api -- env | grep AWS_ACCESS_KEY_ID; test $? -ne 0 | M12: docs/test-evidence/W6-03-identity.txt | N12: Remove service-account binding and restore prior role policy. | O12: Not Started | P12: Week 6 Workload identity task in the end-to-end architecture. After Code Edit Approval, Codex writes only the approved code/configuration/test code for “Configure EKS Pod Identity/IRSA, RBAC and least-privilege service account.”; you run the verification/deployment commands and return the results. Business value: Pods must never contain static AWS credentials. Interview focus: explain where this component sits, how it fails safely and how it is rolled back.
A13: W6-04 | B13: 4 | C13: MUST | D13: Network security | E13: Apply NetworkPolicy and approved ingress/egress boundaries. | F13: Retrieval/model paths should be explicit and least privilege. | G13: Codex (code) + User (execute) | H13: 1 | I13: W6-001 | J13: NET-001, EKS-001 | K13: Denied destination test fails; approved dependencies remain reachable. | L13: kubectl apply --dry-run=server -f deploy/k8s/networkpolicy.yaml | M13: docs/test-evidence/W6-04-network.txt | N13: Restore last-known-good policy; scale down if isolation is uncertain. | O13: Not Started | P13: Week 6 Network security task in the end-to-end architecture. After Code Edit Approval, Codex writes only the approved code/configuration/test code for “Apply NetworkPolicy and approved ingress/egress boundaries.”; you run the verification/deployment commands and return the results. Business value: Retrieval/model paths should be explicit and least privilege. Interview focus: explain where this component sits, how it fails safely and how it is rolled back.
A14: W6-05 | B14: 5 | C14: MUST | D14: Resilience | E14: Configure requests/limits, HPA, PDB and rolling update settings. | F14: Availability and autoscaling must be defined before load/chaos tests. | G14: Codex (code) + User (execute) | H14: 1 | I14: W6-001 | J14: SLO-001 | K14: Schema/policy checks pass and settings have rationale. | L14: kubectl apply --dry-run=server -f deploy/k8s | M14: docs/test-evidence/W6-05-resilience.txt | N14: Rollback manifests and return to last safe replica/settings. | O14: Not Started | P14: Week 6 Resilience task in the end-to-end architecture. After Code Edit Approval, Codex writes only the approved code/configuration/test code for “Configure requests/limits, HPA, PDB and rolling update settings.”; you run the verification/deployment commands and return the results. Business value: Availability and autoscaling must be defined before load/chaos tests. Interview focus: explain where this component sits, how it fails safely and how it is rolled back.
A15: W6-06 | B15: 6 | C15: MUST | D15: Observability platform | E15: Deploy OTel path to CloudWatch/X-Ray plus Prometheus/Grafana/Jaeger option. | F15: Vendor-neutral telemetry supports both AWS and open-source operations. | G15: Codex (code) + User (execute) | H15: 1.25 | I15: W6-002 | J15: OBS-001 | K15: One request trace links API, retrieval and LLM spans. | L15: pytest tests/feature/test_trace_correlation.py -q | M15: docs/test-evidence/W6-06-observability.json | N15: Disable broken exporter; preserve local telemetry path. | O15: Not Started | P15: Week 6 Observability platform task in the end-to-end architecture. After Code Edit Approval, Codex writes only the approved code/configuration/test code for “Deploy OTel path to CloudWatch/X-Ray plus Prometheus/Grafana/Jaeger option.”; you run the verification/deployment commands and return the results. Business value: Vendor-neutral telemetry supports both AWS and open-source operations. Interview focus: explain where this component sits, how it fails safely and how it is rolled back.
A16: W6-07 | B16: 7 | C16: MUST | D16: SRE objectives | E16: Approve SLIs/SLOs, error-budget policy and burn alerts. | F16: Reliability targets must reflect user pain and govern releases. | G16: User (execute) + Codex (guide/code) | H16: 1 | I16: W6-002 | J16: SLO-001, OBS-001 | K16: Availability 99.9%, p95<4s, p99<10s, retrieval p99<750ms, grounded>=95%, isolation/safety=100% are reviewed. | L16: promtool check rules observability/alerts.yml | M16: docs/architecture/slo.md | N16: Disable noisy alert only through reviewed threshold/runbook update. | O16: Not Started | P16: Week 6 SRE objectives task in the end-to-end architecture. After Code Edit Approval, Codex writes only the approved code/configuration/test code for “Approve SLIs/SLOs, error-budget policy and burn alerts.”; you run the verification/deployment commands and return the results. Business value: Reliability targets must reflect user pain and govern releases. Interview focus: explain where this component sits, how it fails safely and how it is rolled back.
A17: W6-08 | B17: 8 | C17: MUST | D17: Runbook | E17: Create and rehearse inference-latency-spike runbook. | F17: An alert is useful only if it drives a safe action. | G17: Codex + User | H17: 1 | I17: W6-002 | J17: OBS-001 | K17: Runbook covers impact, stabilize, stage isolation, rollback and evidence. | L17: Run tabletop and record timeline | M17: runbooks/inference-latency.md | N17: Rollback release/config; use safe refusal/fallback if approved. | O17: Not Started | P17: Week 6 Runbook task in the end-to-end architecture. After Code Edit Approval, Codex writes only the approved code/configuration/test code for “Create and rehearse inference-latency-spike runbook.”; you run the verification/deployment commands and return the results. Business value: An alert is useful only if it drives a safe action. Interview focus: explain where this component sits, how it fails safely and how it is rolled back.
A18: W6-09 | B18: 9 | C18: MUST | D18: Failure/chaos | E18: Stop Qdrant/inject LLM timeout locally; prepare FIS plan without executing it. | F18: Controlled failure proves readiness, bounded retries and alert/runbook quality. | G18: User (execute) + Codex (guide/code) | H18: 1 | I18: W6-002 | J18: FIS-001 | K18: Readiness fails, no retry storm, alert/runbook activates; FIS has tag targets/stop alarms. | L18: pytest tests/feature/test_failure_modes.py -q | M18: docs/test-evidence/W6-09-chaos.txt | N18: Stop experiment, restore dependency, rollback configuration. | O18: Not Started | P18: Week 6 Failure/chaos task in the end-to-end architecture. After Code Edit Approval, Codex writes only the approved code/configuration/test code for “Stop Qdrant/inject LLM timeout locally; prepare FIS plan without executing it.”; you run the verification/deployment commands and return the results. Business value: Controlled failure proves readiness, bounded retries and alert/runbook quality. Interview focus: explain where this component sits, how it fails safely and how it is rolled back.
A19: W6-10 | B19: 10 | C19: MUST | D19: End-to-end validation | E19: Run local and sandbox cited query plus golden evaluation/security suite. | F19: Final proof must combine functionality, quality, security and observability. | G19: User (execute) + Codex (guide/code) | H19: 1.25 | I19: W6-003 | J19: EVAL-001 | K19: No material regression; sandbox query has citations and trace ID. | L19: make final-proof | M19: docs/test-evidence/W6-final-index.md | N19: Block promotion and restore last-known-good release/config. | O19: Not Started | P19: Week 6 End-to-end validation task in the end-to-end architecture. After Code Edit Approval, Codex writes only the approved code/configuration/test code for “Run local and sandbox cited query plus golden evaluation/security suite.”; you run the verification/deployment commands and return the results. Business value: Final proof must combine functionality, quality, security and observability. Interview focus: explain where this component sits, how it fails safely and how it is rolled back.
A20: W6-11 | B20: 11 | C20: MUST | D20: Release rollback drill | E20: Force a safe sandbox regression and restore previous image/configuration. | F20: Rollback must be timed and revalidated before handover. | G20: User | H20: 0.75 | I20: W6-003 | J20: DEST-001 | K20: Last-known-good release passes health, smoke and evaluation gates. | L20: make rollback-release && make validate-sandbox | M20: docs/rollback-records/W6-release.md | N20: Keep failed digest blocked; open defect with evidence. | O20: Not Started | P20: Week 6 owner decision/checkpoint in Release rollback drill. You choose, approve or execute “Force a safe sandbox regression and restore previous image/configuration.” because the decision affects downstream architecture and risk. Codex explains alternatives and may draft approved wording only under the proper approval stage. Business value: Rollback must be timed and revalidated before handover. Interview focus: explain the decision, trade-off and downstream consequence.
A21: W6-12 | B21: 12 | C21: MUST | D21: Full teardown | E21: Run approved destroy sequence, remove bootstrap last and verify cleanliness. | F21: Learning-project cost and residue must stop after use. | G21: User | H21: 1.25 | I21: W5-004 | J21: DEST-001, KMS-001 | K21: No active project resource remains; KMS exception is PendingDeletion only. | L21: make plan-destroy-sandbox; owner approve; make destroy-sandbox; make verify-clean | M21: docs/resource-cleanliness/W6-final.json | N21: Remove residuals in dependency order; never broadly target unverified resources. | O21: Not Started | P21: Week 6 owner decision/checkpoint in Full teardown. You choose, approve or execute “Run approved destroy sequence, remove bootstrap last and verify cleanliness.” because the decision affects downstream architecture and risk. Codex explains alternatives and may draft approved wording only under the proper approval stage. Business value: Learning-project cost and residue must stop after use. Interview focus: explain the decision, trade-off and downstream consequence.
... A23: W6-14 | B23: 14 | C23: MUST | D23: Weekly learning | E23: Complete the Week 6 end-to-end architecture, deployment, SRE and interview teach-back. | F23: Consolidates the full enterprise AI platform into a deployment, reliability, security and business-value narrative. | G23: User (execute) + Codex (guide/code) | H23: 1.5 | I23: WEEKLY-LEARN-001 | J23: None | K23: Owner delivers a 10-minute end-to-end explanation plus failure, rollback, teardown and five interview answers. | L23: Owner teach-back; no command | M23: docs/learning/W6-learning-review.md | N23: No runtime rollback; revise the learning note through document approval if inaccurate. | O23: Not Started | P23: Week 6 learning gate after all implementation and checkpoint work. Codex teaches the business outcome and architecture; the owner completes a teach-back and interview practice. No runtime action is permitted. Business value: converts completed work into reusable understanding and decision ownership.
A25: Grouped prompt sequence — full Main / Code Edit / Document Writing / Final Approval prompts are in 10 Codex Prompts
A26: Order | B26: Prompt ID | C26: Feature | D26: Purpose | E26: Required Inputs | F26: Expected Outputs | G26: Example Usage
A27: 1 | B27: W6-001 | C27: Immutable EKS application deployment | D27: Deploy the verified service with workload identity and safe rollout controls. | E27: EKS cluster/namespace, ECR digest, domain/cert, pod identity choice | F27: Kubernetes/Helm manifests, identity, network policy, health, HPA/PDB and rollback | G27: Review Main Prompt → Column L code approval → owner runs TEST-001 guidance → Column M documents → Column N final approval
A28: 2 | B28: W6-002 | C28: SRE observability, alerts, runbook and chaos plan | D28: Make the platform supportable and measurable. | E28: SLO approval; alert destination; pre-production chaos approval | F28: OTel collector, Prometheus, Grafana, CloudWatch alarms, runbook and FIS plan | G28: Review Main Prompt → Column L code approval → owner runs TEST-001 guidance → Column M documents → Column N final approval
A29: 3 | B29: W6-003 | C29: Final end-to-end proof and handover | D29: Demonstrate architecture, quality, safety, rollback and clean teardown together. | E29: Approved sandbox window and evidence locations | F29: Final validation script, evidence index, ADR updates, demo checklist and architecture brief | G29: Review Main Prompt → Column L code approval → owner runs TEST-001 guidance → Column M documents → Column N final approval
A30: 4 | B30: WEEKLY-LEARN-001 | C30: Week 6 owner learning and interview teach-back | D30: Teach the completed week's business outcome, architecture, decisions, trade-offs and failure/rollback story. | E30: Completed weekly tasks, owner-executed results, approved decisions and documentation | F30: Owner teach-back and optional docs/learning/W6-learning-review.md | G30: Use after all weekly work and final approvals; no code or runtime action

Sheet 09 Architecture Map
A1: Architecture Map and Decision Trace
A2: Objective: turn approved enterprise knowledge into safe, cited answers and controlled actions while every change remains testable, observable, recoverable and removable.
A4: End-to-end flow: approved source → validate/classify/redact → chunk/embed → vector index → authenticate/authorize → retrieve evidence → generate → validate citations/abstain → optionally propose an allowlisted tool → human approval → observe/audit
A6: Layer | B6: Component | C6: Plain-Language Role | D6: Selected Design | E6: Build Week | F6: Decision IDs | G6: Safe Failure Behavior | H6: How We Verify
A7: Knowledge plane | B7: S3 versioned source | C7: Document warehouse for approved source material. | D7: S3 + secure ingestion | E7: Weeks 2,5 | F7: ADR-006, ADR-009 | G7: Quarantine invalid/PII content; do not index it. | H7: Ingestion manifest and PII tests
A8: Knowledge plane | B8: Ingestion + Presidio | C8: Librarian that validates, hashes, classifies, redacts and chunks. | D8: Python local first; Glue/Macie later | E8: Week 2 | F8: ADR-006, ADR-017 | G8: Bad files are quarantined; retries are bounded. | H8: Idempotency/quarantine evidence
A9: Knowledge plane | B9: Sentence Transformers | C9: Converts text meaning to normalized vectors. | D9: Local CPU adapter | E9: Week 2 | F9: ADR-002 | G9: Dimension/model mismatch fails before upsert. | H9: Embedder unit tests
A10: Knowledge plane | B10: Qdrant | C10: Local searchable catalogue for development/integration. | D10: MUST local | E10: Week 2 | F10: ADR-003 | G10: Readiness fails and query returns controlled dependency error. | H10: Qdrant contract/cleanup tests
A11: Knowledge plane | B11: OpenSearch vectors | C11: Private AWS vector and hybrid search target. | D11: MUST plan; SHOULD deploy | E11: Week 5 | F11: ADR-003 | G11: Use last good Terraform/index; do not expose public endpoint. | H11: Terraform plan/policy evidence
A12: Request plane | B12: FastAPI/Uvicorn | C12: Typed front desk for health, query and agent requests. | D12: Thin API boundary | E12: Week 4 | F12: ADR-007 | G12: Deadline/size/concurrency errors are normalized. | H12: API unit/smoke tests
